Workbook
Name www.run: #REF!
Name wrn.Roxydist.: #REF!
Name www.myr: #REF!
Name www.mike: #REF!
Name wrn.HR_HR: #REF!
Name wrn.Mikemurdist.: #REF!
Name wrn.HR_Details.: #REF!
Name www: #REF!
Name wrn.Run._.Rates.: #REF!
Name wrn.Mikemur.: #REF!
Name wrn.Field_PSS.: #REF!
Name wrn.Roxanna.: #REF!
Name wrn.6713_Financials.: #REF!
Name wrn.MYR._.Template.: #REF!
Name wrn.GenDistPac.: #REF!
Name www.ww: #REF!
Name sss: #REF!
Name xxx: #REF!

Sheet Outputs>>
A1: Shasta SaaS Operating Model Outputs for comments and questions, contact Kenn So

Sheet Quarterly Dashboard
A2: =Macro!A2 -> StartUp Co
B3: FY | D3: ='Top line'!D3 -> 2020 | E3: ='Top line'!J3 -> 2021 | I3: ='Top line'!V3 -> 2022 | M3: ='Top line'!AH3 -> 2023
B4: Quarter | D4: Q4 | E4: Q1 | F4: Q2 | G4: Q3 | H4: Q4 | I4: Q1 | J4: Q2 | K4: Q3 | L4: Q4 | M4: Q1 | N4: Q2 | O4: Q3 | P4: Q4
B5: Month | D5: ='Top line'!I5 -> 43861 | E5: =EDATE(D5+1,3)-1 -> 43951 | F5: =EDATE(E5+1,3)-1 -> 44043 | G5: =EDATE(F5+1,3)-1 -> 44135 | H5: =EDATE(G5+1,3)-1 -> 44227 | I5: =EDATE(H5+1,3)-1 -> 44316 | J5: =EDATE(I5+1,3)-1 -> 44408 | K5: =EDATE(J5+1,3)-1 -> 44500 | L5: =EDATE(K5+1,3)-1 -> 44592 | ... P5: =EDATE(O5+1,3)-1 -> 44957
D6: =Team!I6 -> Act | E6: ='Top line'!L6 -> Act | F6: ='Top line'!O6 -> Fcst | G6: ='Top line'!R6 -> Fcst | H6: =Team!U6 -> Fcst | I6: ='Top line'!X6 -> Fcst | J6: ='Top line'!AA6 -> Fcst | K6: ='Top line'!AD6 -> Fcst | L6: ='Top line'!AG6 -> Fcst | M6: ='Top line'!AJ6 -> Fcst | N6: ='Top line'!AM6 -> Fcst | O6: ='Top line'!AP6 -> Fcst | P6: ='Top line'!AS6 -> Fcst
B8: Key metrics
B9: ARR | D9: ='Key metrics'!I9 -> 210000 | E9: ='Top line'!L39 -> 630000 | F9: ='Top line'!O39 -> #VALUE! | G9: ='Top line'!R39 -> #VALUE! | H9: ='Top line'!U39 -> #VALUE! | I9: ='Top line'!X39 -> #VALUE! | J9: ='Top line'!AA39 -> #VALUE! | K9: ='Top line'!AD39 -> #VALUE! | L9: ='Top line'!AG39 -> #VALUE! | M9: ='Top line'!AJ39 -> #VALUE! | N9: ='Top line'!AM39 -> #VALUE! | O9: ='Top line'!AP39 -> #VALUE! | P9: ='Top line'!AS39 -> #VALUE!
B10: Ending cash | D10: ='Key metrics'!I10 -> 1837320 | E10: ='Key metrics'!L10 -> 711980 | F10: ='Key metrics'!O10 -> NA | G10: ='Key metrics'!R10 -> NA | H10: ='Key metrics'!U10 -> NA | I10: ='Key metrics'!X10 -> NA | J10: ='Key metrics'!AA10 -> NA | K10: ='Key metrics'!AD10 -> NA | L10: ='Key metrics'!AG10 -> NA | M10: ='Key metrics'!AJ10 -> NA | N10: ='Key metrics'!AM10 -> NA | O10: ='Key metrics'!AP10 -> NA | P10: ='Key metrics'!AS10 -> NA
B11: Runway months till threshold | D11: ='Key metrics'!I11 -> NA | E11: ='Key metrics'!L11 -> NA | F11: ='Key metrics'!O11 -> NA | G11: ='Key metrics'!R11 -> NA | H11: ='Key metrics'!U11 -> NA | I11: ='Key metrics'!X11 -> NA | J11: ='Key metrics'!AA11 -> NA | K11: ='Key metrics'!AD11 -> NA | L11: ='Key metrics'!AG11 -> NA | M11: ='Key metrics'!AJ11 -> NA | N11: ='Key metrics'!AM11 -> NA | O11: ='Key metrics'!AP11 -> NA | P11: ='Key metrics'!AS11 -> NA
B12: Runway till | C12: {=IFERROR(INDEX('Cash analysis'!$J$5:$AS$5,1,MATCH(1,'Cash analysis'!$J$24:$AS$24,0)),"NA")} -> NA
B14: ARR Spend
B15: ARR
B16: Gross New | E16: =SUM('Top line'!J41:L41) -> 480000 | F16: =SUM('Top line'!M41:O41) -> #VALUE! | G16: =SUM('Top line'!P41:R41) -> #VALUE! | H16: =SUM('Top line'!S41:U41) -> #VALUE! | I16: =SUM('Top line'!V41:X41) -> #VALUE! | J16: =SUM('Top line'!Y41:AA41) -> #VALUE! | K16: =SUM('Top line'!AB41:AD41) -> #VALUE! | L16: =SUM('Top line'!AE41:AG41) -> #VALUE! | M16: =SUM('Top line'!AH41:AJ41) -> #VALUE! | N16: =SUM('Top line'!AK41:AM41) -> #VALUE! | O16: =SUM('Top line'!AN41:AP41) -> #VALUE! | P16: =SUM('Top line'!AQ41:AS41) -> #VALUE!
B17: Expansion | E17: =SUM('Top line'!J42:L42) -> 0 | F17: =SUM('Top line'!M42:O42) -> 0 | G17: =SUM('Top line'!P42:R42) -> 30000 | H17: =SUM('Top line'!S42:U42) -> 37500 | I17: =SUM('Top line'!V42:X42) -> 60000 | J17: =SUM('Top line'!Y42:AA42) -> 0 | K17: =SUM('Top line'!AB42:AD42) -> 0 | L17: =SUM('Top line'!AE42:AG42) -> 0 | M17: =SUM('Top line'!AH42:AJ42) -> 0 | N17: =SUM('Top line'!AK42:AM42) -> 0 | O17: =SUM('Top line'!AN42:AP42) -> 0 | P17: =SUM('Top line'!AQ42:AS42) -> 0
B18: Churn | E18: =SUM('Top line'!J43:L43) -> -60000 | F18: =SUM('Top line'!M43:O43) -> 0 | G18: =SUM('Top line'!P43:R43) -> -60000 | H18: =SUM('Top line'!S43:U43) -> -75000 | I18: =SUM('Top line'!V43:X43) -> -120000 | J18: =SUM('Top line'!Y43:AA43) -> 0 | K18: =SUM('Top line'!AB43:AD43) -> 0 | L18: =SUM('Top line'!AE43:AG43) -> 0 | M18: =SUM('Top line'!AH43:AJ43) -> 0 | N18: =SUM('Top line'!AK43:AM43) -> 0 | O18: =SUM('Top line'!AN43:AP43) -> 0 | P18: =SUM('Top line'!AQ43:AS43) -> 0
B19: Net New | E19: =SUM(E16:E18) -> 420000 | F19: =SUM(F16:F18) -> #VALUE! | G19: =SUM(G16:G18) -> #VALUE! | H19: =SUM(H16:H18) -> #VALUE! | I19: =SUM(I16:I18) -> #VALUE! | J19: =SUM(J16:J18) -> #VALUE! | K19: =SUM(K16:K18) -> #VALUE! | L19: =SUM(L16:L18) -> #VALUE! | ... P19: =SUM(P16:P18) -> #VALUE!
B20: Check | E20: =(E9-D9)=E19 -> TRUE | F20: =(F9-E9)=F19 -> #VALUE! | G20: =(G9-F9)=G19 -> #VALUE! | H20: =(H9-G9)=H19 -> #VALUE! | I20: =(I9-H9)=I19 -> #VALUE! | J20: =(J9-I9)=J19 -> #VALUE! | K20: =(K9-J9)=K19 -> #VALUE! | L20: =(L9-K9)=L19 -> #VALUE! | ... P20: =(P9-O9)=P19 -> #VALUE!
B22: Sales | D22: =SUM(Team!G228:I228)+SUM(Expenses!G129:I129) -> 60000 | E22: =SUM(Team!J228:L228)+SUM(Expenses!J129:L129) -> 136860 | F22: =SUM(Team!M228:O228)+SUM(Expenses!M129:O129) -> #VALUE! | G22: =SUM(Team!P228:R228)+SUM(Expenses!P129:R129) -> #VALUE! | H22: =SUM(Team!S228:U228)+SUM(Expenses!S129:U129) -> #VALUE! | I22: =SUM(Team!V228:X228)+SUM(Expenses!V129:X129) -> #VALUE! | J22: =SUM(Team!Y228:AA228)+SUM(Expenses!Y129:AA129) -> #VALUE! | K22: =SUM(Team!AB228:AD228)+SUM(Expenses!AB129:AD129) -> #VALUE! | L22: =SUM(Team!AE228:AG228)+SUM(Expenses!AE129:AG129) -> #VALUE! | M22: =SUM(Team!AH228:AJ228)+SUM(Expenses!AH129:AJ129) -> #VALUE! | N22: =SUM(Team!AK228:AM228)+SUM(Expenses!AK129:AM129) -> #VALUE! | O22: =SUM(Team!AN228:AP228)+SUM(Expenses!AN129:AP129) -> #VALUE! | P22: =SUM(Team!AQ228:AS228)+SUM(Expenses!AQ129:AS129) -> #VALUE!
B23: Marketing | D23: =SUM(Team!G243:I243)+SUM(Expenses!G130:I130) -> 75000 | E23: =SUM(Team!J243:L243)+SUM(Expenses!J130:L130) -> 237560 | F23: =SUM(Team!M243:O243)+SUM(Expenses!M130:O130) -> 237560 | G23: =SUM(Team!P243:R243)+SUM(Expenses!P130:R130) -> 262560 | H23: =SUM(Team!S243:U243)+SUM(Expenses!S130:U130) -> 262560 | I23: =SUM(Team!V243:X243)+SUM(Expenses!V130:X130) -> 255060 | J23: =SUM(Team!Y243:AA243)+SUM(Expenses!Y130:AA130) -> 317560 | K23: =SUM(Team!AB243:AD243)+SUM(Expenses!AB130:AD130) -> 330060 | L23: =SUM(Team!AE243:AG243)+SUM(Expenses!AE130:AG130) -> 330060 | M23: =SUM(Team!AH243:AJ243)+SUM(Expenses!AH130:AJ130) -> 343393.33 | N23: =SUM(Team!AK243:AM243)+SUM(Expenses!AK130:AM130) -> 410060 | O23: =SUM(Team!AN243:AP243)+SUM(Expenses!AN130:AP130) -> 410060 | P23: =SUM(Team!AQ243:AS243)+SUM(Expenses!AQ130:AS130) -> 410060
B24: Customer Success | D24: =SUM(Team!G297:I297)+SUM(Expenses!G131:I131) -> 75000 | E24: =SUM(Team!J297:L297)+SUM(Expenses!J131:L131) -> 75060 | F24: =SUM(Team!M297:O297)+SUM(Expenses!M131:O131) -> 100060 | G24: =SUM(Team!P297:R297)+SUM(Expenses!P131:R131) -> 112560 | H24: =SUM(Team!S297:U297)+SUM(Expenses!S131:U131) -> 150060 | I24: =SUM(Team!V297:X297)+SUM(Expenses!V131:X131) -> 100060 | J24: =SUM(Team!Y297:AA297)+SUM(Expenses!Y131:AA131) -> 187560 | K24: =SUM(Team!AB297:AD297)+SUM(Expenses!AB131:AD131) -> 187560 | L24: =SUM(Team!AE297:AG297)+SUM(Expenses!AE131:AG131) -> 225060 | M24: =SUM(Team!AH297:AJ297)+SUM(Expenses!AH131:AJ131) -> 183393.33 | N24: =SUM(Team!AK297:AM297)+SUM(Expenses!AK131:AM131) -> 312560 | O24: =SUM(Team!AN297:AP297)+SUM(Expenses!AN131:AP131) -> 312560 | P24: =SUM(Team!AQ297:AS297)+SUM(Expenses!AQ131:AS131) -> 350060
B25: Total GTM Expense | D25: =SUM(D22:D24) -> 210000 | E25: =SUM(E22:E24) -> 449480 | F25: =SUM(F22:F24) -> #VALUE! | G25: =SUM(G22:G24) -> #VALUE! | H25: =SUM(H22:H24) -> #VALUE! | I25: =SUM(I22:I24) -> #VALUE! | J25: =SUM(J22:J24) -> #VALUE! | K25: =SUM(K22:K24) -> #VALUE! | ... P25: =SUM(P22:P24) -> #VALUE!
B27: Net cash burn | E27: =SUM('Cash analysis'!J25:L25) -> -1125340 | F27: =SUM('Cash analysis'!M25:O25) -> #VALUE! | G27: =SUM('Cash analysis'!P25:R25) -> #VALUE! | H27: =SUM('Cash analysis'!S25:U25) -> #VALUE! | I27: =SUM('Cash analysis'!V25:X25) -> #VALUE! | J27: =SUM('Cash analysis'!Y25:AA25) -> #VALUE! | K27: =SUM('Cash analysis'!AB25:AD25) -> #VALUE! | L27: =SUM('Cash analysis'!AE25:AG25) -> #VALUE! | M27: =SUM('Cash analysis'!AH25:AJ25) -> #VALUE! | N27: =SUM('Cash analysis'!AK25:AM25) -> #VALUE! | O27: =SUM('Cash analysis'!AN25:AP25) -> #VALUE! | P27: =SUM('Cash analysis'!AQ25:AS25) -> #VALUE!
B28: Gross cash burn | E28: =-SUM('Cash analysis'!J19:L19) -> -1745340 | F28: =-SUM('Cash analysis'!M19:O19) -> #VALUE! | G28: =-SUM('Cash analysis'!P19:R19) -> #VALUE! | H28: =-SUM('Cash analysis'!S19:U19) -> #VALUE! | I28: =-SUM('Cash analysis'!V19:X19) -> #VALUE! | J28: =-SUM('Cash analysis'!Y19:AA19) -> #VALUE! | K28: =-SUM('Cash analysis'!AB19:AD19) -> #VALUE! | L28: =-SUM('Cash analysis'!AE19:AG19) -> #VALUE! | M28: =-SUM('Cash analysis'!AH19:AJ19) -> #VALUE! | N28: =-SUM('Cash analysis'!AK19:AM19) -> #VALUE! | O28: =-SUM('Cash analysis'!AN19:AP19) -> #VALUE! | P28: =-SUM('Cash analysis'!AQ19:AS19) -> #VALUE!
B30: SaaS metrics
B31: Gross Magic Number | E31: =IFERROR(SUM(E16:E17)/SUM(D22:D24),"NA") -> 2.2857143 | F31: =IFERROR(SUM(F16:F17)/SUM(E22:E24),"NA") -> NA | G31: =IFERROR(SUM(G16:G17)/SUM(F22:F24),"NA") -> NA | H31: =IFERROR(SUM(H16:H17)/SUM(G22:G24),"NA") -> NA | I31: =IFERROR(SUM(I16:I17)/SUM(H22:H24),"NA") -> NA | J31: =IFERROR(SUM(J16:J17)/SUM(I22:I24),"NA") -> NA | K31: =IFERROR(SUM(K16:K17)/SUM(J22:J24),"NA") -> NA | L31: =IFERROR(SUM(L16:L17)/SUM(K22:K24),"NA") -> NA | ... P31: =IFERROR(SUM(P16:P17)/SUM(O22:O24),"NA") -> NA
B32: Magic Number | E32: =IFERROR(E19/SUM(D25),"NA") -> 2 | F32: =IFERROR(F19/SUM(E25),"NA") -> NA | G32: =IFERROR(G19/SUM(F25),"NA") -> NA | H32: =IFERROR(H19/SUM(G25),"NA") -> NA | I32: =IFERROR(I19/SUM(H25),"NA") -> NA | J32: =IFERROR(J19/SUM(I25),"NA") -> NA | K32: =IFERROR(K19/SUM(J25),"NA") -> NA | L32: =IFERROR(L19/SUM(K25),"NA") -> NA | ... P32: =IFERROR(P19/SUM(O25),"NA") -> NA
B33: CAC Ratio | E33: =IFERROR(E32*Macro!$D$8,"NA") -> 1.6 | F33: =IFERROR(F32*Macro!$D$8,"NA") -> NA | G33: =IFERROR(G32*Macro!$D$8,"NA") -> NA | H33: =IFERROR(H32*Macro!$D$8,"NA") -> NA | I33: =IFERROR(I32*Macro!$D$8,"NA") -> NA | J33: =IFERROR(J32*Macro!$D$8,"NA") -> NA | K33: =IFERROR(K32*Macro!$D$8,"NA") -> NA | L33: =IFERROR(L32*Macro!$D$8,"NA") -> NA | ... P33: =IFERROR(P32*Macro!$D$8,"NA") -> NA
B34: Payback Period (Months) | E34: =IFERROR(1/E33*12,"NA") -> 7.5 | F34: =IFERROR(1/F33*12,"NA") -> NA | G34: =IFERROR(1/G33*12,"NA") -> NA | H34: =IFERROR(1/H33*12,"NA") -> NA | I34: =IFERROR(1/I33*12,"NA") -> NA | J34: =IFERROR(1/J33*12,"NA") -> NA | K34: =IFERROR(1/K33*12,"NA") -> NA | L34: =IFERROR(1/L33*12,"NA") -> NA | ... P34: =IFERROR(1/P33*12,"NA") -> NA
B36: High-Level Annual Sales Efficiency | H36: =IFERROR(SUM(E19:H19)/SUM(E25:H25),"NA") -> NA | L36: =IFERROR(SUM(I19:L19)/SUM(I25:L25),"NA") -> NA | P36: =IFERROR(SUM(M19:P19)/SUM(M25:P25),"NA") -> NA
B37: Net New ARR vs. Operating Cash Flow | E37: =IFERROR((E19/E27)*-1,"NA") -> 0.37322054 | F37: =IFERROR((F19/F27)*-1,"NA") -> NA | G37: =IFERROR((G19/G27)*-1,"NA") -> NA | H37: =IFERROR((H19/H27)*-1,"NA") -> NA | J37: =IFERROR((J19/J27)*-1,"NA") -> NA | K37: =IFERROR((K19/K27)*-1,"NA") -> NA | L37: =IFERROR((L19/L27)*-1,"NA") -> NA | N37: =IFERROR((N19/N27)*-1,"NA") -> NA | O37: =IFERROR((O19/O27)*-1,"NA") -> NA | P37: =IFERROR((P19/P27)*-1,"NA") -> NA
B38: High-Level Annual Capital Efficiency | H38: =IFERROR(-SUM(E19:H19)/SUM(E27:H27),"NA") -> NA | L38: =IFERROR(-SUM(I19:L19)/SUM(I27:L27),"NA") -> NA | P38: =IFERROR(-SUM(M19:P19)/SUM(M27:P27),"NA") -> NA
B40: LTV CAC
B41: # of new customers | E41: =SUM('Top line'!J15:L15) -> 12 | F41: =SUM('Top line'!M15:O15) -> #VALUE! | G41: =SUM('Top line'!P15:R15) -> #VALUE! | H41: =SUM('Top line'!S15:U15) -> #VALUE! | I41: =SUM('Top line'!V15:X15) -> #VALUE! | J41: =SUM('Top line'!Y15:AA15) -> #VALUE! | K41: =SUM('Top line'!AB15:AD15) -> #VALUE! | L41: =SUM('Top line'!AE15:AG15) -> #VALUE! | M41: =SUM('Top line'!AH15:AJ15) -> #VALUE! | N41: =SUM('Top line'!AK15:AM15) -> #VALUE! | O41: =SUM('Top line'!AN15:AP15) -> #VALUE! | P41: =SUM('Top line'!AQ15:AS15) -> #VALUE!
B42: ARR per customer | E42: =E16/E41 -> 40000 | F42: =F16/F41 -> #VALUE! | G42: =G16/G41 -> #VALUE! | H42: =H16/H41 -> #VALUE! | I42: =I16/I41 -> #VALUE! | J42: =J16/J41 -> #VALUE! | K42: =K16/K41 -> #VALUE! | L42: =L16/L41 -> #VALUE! | ... P42: =P16/P41 -> #VALUE!
B43: (x) years | E43: =Macro!$D$7 -> 3 | F43: =Macro!$D$7 -> 3 | G43: =Macro!$D$7 -> 3 | H43: =Macro!$D$7 -> 3 | I43: =Macro!$D$7 -> 3 | J43: =Macro!$D$7 -> 3 | K43: =Macro!$D$7 -> 3 | L43: =Macro!$D$7 -> 3 | ... P43: =Macro!$D$7 -> 3
B44: Lifetime ARR (no upsell & churn) | E44: =IFERROR(E42*E43,"NA") -> 120000 | F44: =IFERROR(F42*F43,"NA") -> NA | G44: =IFERROR(G42*G43,"NA") -> NA | H44: =IFERROR(H42*H43,"NA") -> NA | I44: =IFERROR(I42*I43,"NA") -> NA | J44: =IFERROR(J42*J43,"NA") -> NA | K44: =IFERROR(K42*K43,"NA") -> NA | L44: =IFERROR(L42*L43,"NA") -> NA | ... P44: =IFERROR(P42*P43,"NA") -> NA
B45: (x) Gross Margin - Long Term | E45: =Macro!$D$8 -> 0.8 | F45: =Macro!$D$8 -> 0.8 | G45: =Macro!$D$8 -> 0.8 | H45: =Macro!$D$8 -> 0.8 | I45: =Macro!$D$8 -> 0.8 | J45: =Macro!$D$8 -> 0.8 | K45: =Macro!$D$8 -> 0.8 | L45: =Macro!$D$8 -> 0.8 | ... P45: =Macro!$D$8 -> 0.8
B46: Gross Margin CLTV | E46: =IFERROR(E44*E45,"NA") -> 96000 | F46: =IFERROR(F44*F45,"NA") -> NA | G46: =IFERROR(G44*G45,"NA") -> NA | H46: =IFERROR(H44*H45,"NA") -> NA | I46: =IFERROR(I44*I45,"NA") -> NA | J46: =IFERROR(J44*J45,"NA") -> NA | K46: =IFERROR(K44*K45,"NA") -> NA | L46: =IFERROR(L44*L45,"NA") -> NA | ... P46: =IFERROR(P44*P45,"NA") -> NA
B47: CAC per Customer | E47: =IFERROR(SUM(D22:D24)/E41,"NA") -> 17500 | F47: =IFERROR(SUM(E22:E24)/F41,"NA") -> NA | G47: =IFERROR(SUM(F22:F24)/G41,"NA") -> NA | H47: =IFERROR(SUM(G22:G24)/H41,"NA") -> NA | I47: =IFERROR(SUM(H22:H24)/I41,"NA") -> NA | J47: =IFERROR(SUM(I22:I24)/J41,"NA") -> NA | K47: =IFERROR(SUM(J22:J24)/K41,"NA") -> NA | L47: =IFERROR(SUM(K22:K24)/L41,"NA") -> NA | ... P47: =IFERROR(SUM(O22:O24)/P41,"NA") -> NA
B48: CLTV/CAC | E48: =IFERROR(E46/E47,"NA") -> 5.4857143 | F48: =IFERROR(F46/F47,"NA") -> NA | G48: =IFERROR(G46/G47,"NA") -> NA | H48: =IFERROR(H46/H47,"NA") -> NA | I48: =IFERROR(I46/I47,"NA") -> NA | J48: =IFERROR(J46/J47,"NA") -> NA | K48: =IFERROR(K46/K47,"NA") -> NA | L48: =IFERROR(L46/L47,"NA") -> NA | ... P48: =IFERROR(P46/P47,"NA") -> NA

Sheet Key metrics
A2: =Macro!A2 -> StartUp Co
B3: FY | D3: ='Top line'!D3 -> 2020 | J3: ='Top line'!J3 -> 2021 | V3: ='Top line'!V3 -> 2022 | AH3: ='Top line'!AH3 -> 2023
C4: Quarter | D4: ='Top line'!D4 -> 3 | G4: ='Top line'!G4 -> 4 | J4: ='Top line'!J4 -> 1 | M4: ='Top line'!M4 -> 2 | P4: ='Top line'!P4 -> 3 | S4: ='Top line'!S4 -> 4 | V4: ='Top line'!V4 -> 1 | Y4: ='Top line'!Y4 -> 2 | AB4: ='Top line'!AB4 -> 3 | AE4: ='Top line'!AE4 -> 4 | AH4: ='Top line'!AH4 -> 1 | AK4: ='Top line'!AK4 -> 2 | AN4: ='Top line'!AN4 -> 3 | AQ4: ='Top line'!AQ4 -> 4
C5: Month | D5: ='Top line'!D5 -> 43707 | E5: ='Top line'!E5 -> 43738 | F5: ='Top line'!F5 -> 43769 | G5: ='Top line'!G5 -> 43799 | H5: ='Top line'!H5 -> 43830 | I5: ='Top line'!I5 -> 43861 | J5: ='Top line'!J5 -> 43890 | K5: ='Top line'!K5 -> 43921 | ... AS5: ='Top line'!AS5 -> 44957
D6: Act | E6: Act | F6: Act | G6: Act | H6: Act | I6: Act | J6: Act | K6: Act | L6: Act | M6: Fcst | N6: Fcst | O6: Fcst | P6: Fcst | Q6: Fcst | R6: Fcst | S6: Fcst | T6: Fcst | U6: Fcst | V6: Fcst | W6: Fcst | X6: Fcst | Y6: Fcst | Z6: Fcst | AA6: Fcst | AB6: Fcst | AC6: Fcst | AD6: Fcst | AE6: Fcst | AF6: Fcst | AG6: Fcst | AH6: Fcst | AI6: Fcst | AJ6: Fcst | AK6: Fcst | AL6: Fcst | AM6: Fcst | AN6: Fcst | AO6: Fcst | AP6: Fcst | AQ6: Fcst | AR6: Fcst | AS6: Fcst
B8: Key metrics
C9: ARR | G9: ='Top line'!G39 -> 110000 | H9: ='Top line'!H39 -> 160000 | I9: ='Top line'!I39 -> 210000 | J9: ='Top line'!J39 -> 350000 | K9: ='Top line'!K39 -> 490000 | L9: ='Top line'!L39 -> 630000 | M9: ='Top line'!M39 -> #VALUE! | N9: ='Top line'!N39 -> #VALUE! | ... AS9: ='Top line'!AS39 -> #VALUE!
C10: Ending Cash | G10: =IFERROR('Cash analysis'!G23,"NA") -> 2612440 | H10: =IFERROR('Cash analysis'!H23,"NA") -> 2224880 | I10: =IFERROR('Cash analysis'!I23,"NA") -> 1837320 | J10: =IFERROR('Cash analysis'!J23,"NA") -> 1449760 | K10: =IFERROR('Cash analysis'!K23,"NA") -> 1062200 | L10: =IFERROR('Cash analysis'!L23,"NA") -> 711980 | M10: =IFERROR('Cash analysis'!M23,"NA") -> NA | N10: =IFERROR('Cash analysis'!N23,"NA") -> NA | ... AS10: =IFERROR('Cash analysis'!AS23,"NA") -> NA
C11: Runway in months | G11: {=IFERROR(MAX((INDEX('Cash analysis'!$J$5:$AS$5,1,MATCH(1,'Cash analysis'!$J$24:$AS$24,0))-G5)/30,0),"NA")} -> NA | H11: {=IFERROR(MAX((INDEX('Cash analysis'!$J$5:$AS$5,1,MATCH(1,'Cash analysis'!$J$24:$AS$24,0))-H5)/30,0),"NA")} -> NA | I11: {=IFERROR(MAX((INDEX('Cash analysis'!$J$5:$AS$5,1,MATCH(1,'Cash analysis'!$J$24:$AS$24,0))-I5)/30,0),"NA")} -> NA | J11: {=IFERROR(MAX((INDEX('Cash analysis'!$J$5:$AS$5,1,MATCH(1,'Cash analysis'!$J$24:$AS$24,0))-J5)/30,0),"NA")} -> NA | K11: {=IFERROR(MAX((INDEX('Cash analysis'!$J$5:$AS$5,1,MATCH(1,'Cash analysis'!$J$24:$AS$24,0))-K5)/30,0),"NA")} -> NA | L11: {=IFERROR(MAX((INDEX('Cash analysis'!$J$5:$AS$5,1,MATCH(1,'Cash analysis'!$J$24:$AS$24,0))-L5)/30,0),"NA")} -> NA | M11: {=IFERROR(MAX((INDEX('Cash analysis'!$J$5:$AS$5,1,MATCH(1,'Cash analysis'!$J$24:$AS$24,0))-M5)/30,0),"NA")} -> NA | N11: {=IFERROR(MAX((INDEX('Cash analysis'!$J$5:$AS$5,1,MATCH(1,'Cash analysis'!$J$24:$AS$24,0))-N5)/30,0),"NA")} -> NA | ... AS11: {=IFERROR(MAX((INDEX('Cash analysis'!$J$5:$AS$5,1,MATCH(1,'Cash analysis'!$J$24:$AS$24,0))-AS5)/30,0),"NA")} -> NA

Sheet Inputs>>
A1: Shasta SaaS Operating Model Inputs for comments and questions, contact Kenn So

Sheet Macro
A2: StartUp Co
A5: Sales Scenario Toggle | D5: 1
A6: Minimum cash threshold | D6: 100000
A7: Customer life (years) | D7: 3
A8: Long-term gross margin | D8: 0.8
A10: Sales
D11: Scenario 1 | E11: Scenario 2 | F11: Scenario 3 | H11: Selected Scenario
B12: AE assumptions
B13: Capacity of ramping AE | D13: 0 | E13: 0 | F13: 0 | H13: =OFFSET(C13,0,$D$5) -> 0
B14: AE ramp time (months) | D14: 6 | E14: 6 | F14: 6 | H14: =OFFSET(C14,0,$D$5) -> 6
B15: Monthly deals/ ramped AE | D15: 3 | E15: 3 | F15: 5 | H15: =OFFSET(C15,0,$D$5) -> 3
B17: Deal assumptions
B18: Landing CV | D18: 50000 | E18: 50000 | F18: 50000 | H18: =OFFSET(C18,0,$D$5) -> 50000
B19: Months to upsell | D19: 12 | E19: 12 | F19: 12 | H19: =OFFSET(C19,0,$D$5) -> 12
B20: Logo churn rate | D20: 0.1 | E20: 0.1 | F20: 0.1 | H20: =OFFSET(C20,0,$D$5) -> 0.1 | I20: Rounded up for # of customers
B21: Collection delay (months) | D21: 1 | E21: 1 | F21: 1 | H21: =OFFSET(C21,0,$D$5) -> 1
B22: % of customers upsell | D22: 0.25 | E22: 0.25 | F22: 0.25 | H22: =OFFSET(C22,0,$D$5) -> 0.25 | I22: Rounded up for # of customers
B23: % value of upsell | D23: 0.5 | E23: 0.5 | F23: 0.5 | H23: =OFFSET(C23,0,$D$5) -> 0.5
B25: Sales team ratios
B26: AE manager to AE ratio | D26: =1/6 -> 0.16666667 | E26: =1/6 -> 0.16666667 | F26: =1/6 -> 0.16666667 | H26: =OFFSET(C26,0,$D$5) -> 0.16666667
B27: SE to AE ratio | D27: 0.5 | E27: 0.5 | F27: 0.5 | H27: =OFFSET(C27,0,$D$5) -> 0.5
B28: SE manager to SE ratio | D28: 0.1 | E28: 0.1 | F28: 0.1 | H28: =OFFSET(C28,0,$D$5) -> 0.1
B30: New bookings commission
B31: =B57 -> CRO | D31: 0.05 | E31: 0.05 | F31: 0.05 | H31: =OFFSET(C31,0,$D$5) -> 0.05
B32: =B58 -> AE | D32: 0.15 | E32: 0.15 | F32: 0.15 | H32: =OFFSET(C32,0,$D$5) -> 0.15
B33: =B59 -> AE manager | D33: 0.02 | E33: 0.02 | F33: 0.02 | H33: =OFFSET(C33,0,$D$5) -> 0.02
B34: =B60 -> SE | D34: 0.01 | E34: 0.01 | F34: 0.01 | H34: =OFFSET(C34,0,$D$5) -> 0.01
B35: =B61 -> SE manager | D35: 0.02 | E35: 0.02 | F35: 0.02 | H35: =OFFSET(C35,0,$D$5) -> 0.02
B36: =B62 -> Sales Ops | D36: 0 | E36: 0 | F36: 0 | H36: =OFFSET(C36,0,$D$5) -> 0
B37: =B63 -> [XX] | D37: 0 | E37: 0 | F37: 0 | H37: =OFFSET(C37,0,$D$5) -> 0
B38: =B64 -> [XX] | D38: 0 | E38: 0 | F38: 0 | H38: =OFFSET(C38,0,$D$5) -> 0
B39: =B65 -> [XX] | D39: 0 | E39: 0 | F39: 0 | H39: =OFFSET(C39,0,$D$5) -> 0
B40: =B66 -> [XX] | D40: 0 | E40: 0 | F40: 0 | H40: =OFFSET(C40,0,$D$5) -> 0
B41: =B67 -> [XX] | D41: 0 | E41: 0 | F41: 0 | H41: =OFFSET(C41,0,$D$5) -> 0
B42: =B68 -> [XX] | D42: 0 | E42: 0 | F42: 0 | H42: =OFFSET(C42,0,$D$5) -> 0
B43: Total | D43: =SUM(D31:D42) -> 0.25 | E43: =SUM(E31:E42) -> 0.25 | F43: =SUM(F31:F42) -> 0.25 | H43: =SUM(H31:H42) -> 0.25 | I43: % of collections from gross new bookings when booked/signed
A45: COGS & Benefits
B46: COGS - Others | D46: 0 | E46: / customer / year
B47: COGS - Hosting Services | D47: 17500 | E47: per month
B48: COGS - % of bookings through Salesforce | D48: 0 | E48: paid at time of booking collection
B49: COGS - Salesforce bookings charge % of sales | D49: 0.15
B50: Benefits & taxes | D50: 0.2 | E50: % of salaries
B51: % Commission excluded from benefits | D51: 0
B52: Bonus month | D52: 2 | E52: Note: Only input 1-12
A54: Salaries
D55: Starting annual | E55: Bonus (See Bonus month) | F55: Traveler Flag
B56: Sales
B57: CRO | D57: 200000 | E57: 0.1 | F57: 1
B58: AE | D58: 80000 | E58: 0.1 | F58: 1
B59: AE manager | D59: 150000 | E59: 0.1 | F59: 1
B60: SE | D60: 80000 | E60: 0.1 | F60: 1
B61: SE manager | D61: 150000 | E61: 0.1 | F61: 1
B62: Sales Ops | D62: 150000 | E62: 0.1 | F62: 1
B63: [XX]
B64: [XX]
B65: [XX]
B66: [XX]
B67: [XX]
B68: [XX]
B70: Marketing
B71: CMO | D71: 200000 | E71: 0.1
B72: Director of Demand | D72: 150000 | E72: 0.1
B73: SDR | D73: 150000 | E73: 0.1
B74: Creative | D74: 150000 | E74: 0.1
B75: PMM / VP Marketing | D75: 150000 | E75: 0.1
B76: Field | D76: 150000 | E76: 0.1
B77: [XX]
B78: [XX]
B79: [XX]
B80: [XX]
B81: [XX]
B82: [XX]
B84: Engineering
B85: Chief Architect | D85: 200000 | E85: 0.1
B86: VP Engineering | D86: 200000 | E86: 0.1
B87: Founding Frontend Engineer | D87: 150000 | E87: 0.1
B88: Founding Backend Engineer | D88: 150000 | E88: 0.1
B89: Founding API Engineer | D89: 150000 | E89: 0.1
B90: Platform Engineer | D90: 150000 | E90: 0.1
B91: Head of Analytics | D91: 150000 | E91: 0.1
B92: Quality Assurance Lead | D92: 150000 | E92: 0.1
B93: Frontend Engr | D93: 150000 | E93: 0.1
B94: DevOps Engineer | D94: 150000 | E94: 0.1
B95: MobileApps Engineer | D95: 150000 | E95: 0.1
B96: API Engineer | D96: 150000 | E96: 0.1
... B103: Engr Manager | D103: 150000 | E103: 0.1
B104: [XX]
B105: [XX]
B106: [XX]
B107: [XX]
B108: [XX]
B109: [XX]
B111: Product
B112: Founding Product Designer | D112: 200000 | E112: 0.1
B113: Product Manager | D113: 150000 | E113: 0.1
B114: Tech Writer | D114: 150000 | E114: 0.1
B115: [XX]
B116: [XX]
B117: [XX]
B118: [XX]
...

Sheet Top line
A2: =Macro!A2 -> StartUp Co
B3: FY | D3: 2020 | J3: 2021 | V3: 2022 | AH3: 2023
B4: Quarter | D4: 3 | E4: 3 | F4: 3 | G4: 4 | H4: 4 | I4: 4 | J4: 1 | K4: 1 | L4: 1 | M4: 2 | N4: 2 | O4: 2 | P4: 3 | Q4: 3 | R4: 3 | S4: 4 | T4: 4 | U4: 4 | V4: 1 | W4: 1 | X4: 1 | Y4: 2 | Z4: 2 | AA4: 2 | AB4: 3 | AC4: 3 | AD4: 3 | AE4: 4 | AF4: 4 | AG4: 4 | AH4: 1 | AI4: 1 | AJ4: 1 | AK4: 2 | AL4: 2 | AM4: 2 | AN4: 3 | AO4: 3 | AP4: 3 | AQ4: 4 | AR4: 4 | AS4: 4
B5: Month | D5: 43707 | E5: =EOMONTH(D5,1) -> 43738 | F5: =EOMONTH(E5,1) -> 43769 | G5: =EOMONTH(F5,1) -> 43799 | H5: =EOMONTH(G5,1) -> 43830 | I5: =EOMONTH(H5,1) -> 43861 | J5: =EOMONTH(I5,1) -> 43890 | K5: =EOMONTH(J5,1) -> 43921 | L5: =EOMONTH(K5,1) -> 43951 | ... AS5: =EOMONTH(AR5,1) -> 44957
D6: Act | E6: Act | F6: Act | G6: Act | H6: Act | I6: Act | J6: Act | K6: Act | L6: Act | M6: Fcst | N6: Fcst | O6: Fcst | P6: Fcst | Q6: Fcst | R6: Fcst | S6: Fcst | T6: Fcst | U6: Fcst | V6: Fcst | W6: Fcst | X6: Fcst | Y6: Fcst | Z6: Fcst | AA6: Fcst | AB6: Fcst | AC6: Fcst | AD6: Fcst | AE6: Fcst | AF6: Fcst | AG6: Fcst | AH6: Fcst | AI6: Fcst | AJ6: Fcst | AK6: Fcst | AL6: Fcst | AM6: Fcst | AN6: Fcst | AO6: Fcst | AP6: Fcst | AQ6: Fcst | AR6: Fcst | AS6: Fcst
B8: Bookings
C9: New AEs | E9: =Team!E19 -> 0 | F9: =Team!F19 -> 0 | G9: =Team!G19 -> 0 | H9: =Team!H19 -> 0 | I9: =Team!I19 -> 0 | J9: =Team!J19 -> 0 | K9: =Team!K19 -> 0 | L9: =Team!L19 -> 0 | ... AS9: =Team!AS19 -> 0
C10: Acct. exec. | E10: =Team!E118 -> 2 | F10: =Team!F118 -> 2 | G10: =Team!G118 -> 2 | H10: =Team!H118 -> 2 | I10: =Team!I118 -> 2 | J10: =Team!J118 -> 2 | K10: =Team!K118 -> 2 | L10: =Team!L118 -> 2 | ... AS10: =Team!AS118 -> 7
C11: Ramping AE | F11: =SUM(OFFSET(F9,0,0,1,-Macro!$H$14)) -> #VALUE! | G11: =SUM(OFFSET(G9,0,0,1,-Macro!$H$14)) -> #VALUE! | H11: =SUM(OFFSET(H9,0,0,1,-Macro!$H$14)) -> #VALUE! | I11: =SUM(OFFSET(I9,0,0,1,-Macro!$H$14)) -> #VALUE! | J11: =SUM(OFFSET(J9,0,0,1,-MAX(Macro!$H$14,1))) -> #VALUE! | K11: =SUM(OFFSET(K9,0,0,1,-MAX(Macro!$H$14,1))) -> #VALUE! | L11: =SUM(OFFSET(L9,0,0,1,-MAX(Macro!$H$14,1))) -> #VALUE! | M11: =SUM(OFFSET(M9,0,0,1,-MAX(Macro!$H$14,1))) -> #VALUE! | N11: =SUM(OFFSET(N9,0,0,1,-MAX(Macro!$H$14,1))) -> #VALUE! | O11: =SUM(OFFSET(O9,0,0,1,-MAX(Macro!$H$14,1))) -> #VALUE! | P11: =SUM(OFFSET(P9,0,0,1,-MAX(Macro!$H$14,1))) -> #VALUE! | Q11: =SUM(OFFSET(Q9,0,0,1,-MAX(Macro!$H$14,1))) -> #VALUE! | ... AS11: =SUM(OFFSET(AS9,0,0,1,-MAX(Macro!$H$14,1))) -> #VALUE!
C12: Ramped AE | F12: =F10-F11 -> #VALUE! | G12: =G10-G11 -> #VALUE! | H12: =H10-H11 -> #VALUE! | I12: =I10-I11 -> #VALUE! | J12: =J10-J11 -> #VALUE! | K12: =K10-K11 -> #VALUE! | L12: =L10-L11 -> #VALUE! | M12: =M10-M11 -> #VALUE! | ... AS12: =AS10-AS11 -> #VALUE!
C14: New Bookings
C15: New customers | D15: 1 | E15: 1 | F15: 1 | G15: 2 | H15: 2 | I15: 2 | J15: 4 | K15: 4 | L15: 4 | M15: =ROUND(M11*Macro!$H$13+M12*Macro!$H$15,0) -> #VALUE! | N15: =ROUND(N11*Macro!$H$13+N12*Macro!$H$15,0) -> #VALUE! | O15: =ROUND(O11*Macro!$H$13+O12*Macro!$H$15,0) -> #VALUE! | P15: =ROUND(P11*Macro!$H$13+P12*Macro!$H$15,0) -> #VALUE! | Q15: =ROUND(Q11*Macro!$H$13+Q12*Macro!$H$15,0) -> #VALUE! | R15: =ROUND(R11*Macro!$H$13+R12*Macro!$H$15,0) -> #VALUE! | S15: =ROUND(S11*Macro!$H$13+S12*Macro!$H$15,0) -> #VALUE! | T15: =ROUND(T11*Macro!$H$13+T12*Macro!$H$15,0) -> #VALUE! | ... AS15: =ROUND(AS11*Macro!$H$13+AS12*Macro!$H$15,0) -> #VALUE!
C16: Landing ACV / customer | D16: 20000 | E16: 20000 | F16: 20000 | G16: 25000 | H16: 25000 | I16: 25000 | J16: 40000 | K16: 40000 | L16: 40000 | M16: =Macro!$H$18 -> 50000 | N16: =Macro!$H$18 -> 50000 | O16: =Macro!$H$18 -> 50000 | P16: =Macro!$H$18 -> 50000 | Q16: =Macro!$H$18 -> 50000 | R16: =Macro!$H$18 -> 50000 | S16: =Macro!$H$18 -> 50000 | T16: =Macro!$H$18 -> 50000 | ... AS16: =Macro!$H$18 -> 50000
C17: New bookings | D17: =D15*D16 -> 20000 | E17: =E15*E16 -> 20000 | F17: =F15*F16 -> 20000 | G17: =G15*G16 -> 50000 | H17: =H15*H16 -> 50000 | I17: =I15*I16 -> 50000 | J17: =J15*J16 -> 160000 | K17: =K15*K16 -> 160000 | ... AS17: =AS15*AS16 -> #VALUE!
C19: Expansion Bookings
C20: # of customers upselling | D20: 0 | E20: 0 | F20: 0 | G20: 0 | H20: 0 | I20: 0 | J20: 0 | K20: 0 | L20: 0 | M20: =ROUNDUP(IF(ISNUMBER(OFFSET(M15,0,-Macro!$H$19))=TRUE,OFFSET(M15,0,-Macro!$H$19)*Macro!$H$22,0),0) -> 0 | N20: =ROUNDUP(IF(ISNUMBER(OFFSET(N15,0,-Macro!$H$19))=TRUE,OFFSET(N15,0,-Macro!$H$19)*Macro!$H$22,0),0) -> 0 | O20: =ROUNDUP(IF(ISNUMBER(OFFSET(O15,0,-Macro!$H$19))=TRUE,OFFSET(O15,0,-Macro!$H$19)*Macro!$H$22,0),0) -> 0 | P20: =ROUNDUP(IF(ISNUMBER(OFFSET(P15,0,-Macro!$H$19))=TRUE,OFFSET(P15,0,-Macro!$H$19)*Macro!$H$22,0),0) -> 1 | Q20: =ROUNDUP(IF(ISNUMBER(OFFSET(Q15,0,-Macro!$H$19))=TRUE,OFFSET(Q15,0,-Macro!$H$19)*Macro!$H$22,0),0) -> 1 | R20: =ROUNDUP(IF(ISNUMBER(OFFSET(R15,0,-Macro!$H$19))=TRUE,OFFSET(R15,0,-Macro!$H$19)*Macro!$H$22,0),0) -> 1 | S20: =ROUNDUP(IF(ISNUMBER(OFFSET(S15,0,-Macro!$H$19))=TRUE,OFFSET(S15,0,-Macro!$H$19)*Macro!$H$22,0),0) -> 1 | T20: =ROUNDUP(IF(ISNUMBER(OFFSET(T15,0,-Macro!$H$19))=TRUE,OFFSET(T15,0,-Macro!$H$19)*Macro!$H$22,0),0) -> 1 | ... AS20: =ROUNDUP(IF(ISNUMBER(OFFSET(AS15,0,-Macro!$H$19))=TRUE,OFFSET(AS15,0,-Macro!$H$19)*Macro!$H$22,0),0) -> 0
C21: Expansion ACV | D21: 0 | E21: 0 | F21: 0 | G21: 0 | H21: 0 | I21: 0 | J21: 0 | K21: 0 | L21: 0 | M21: =IF(ISNUMBER(OFFSET(M16,0,-Macro!$H$19))=TRUE,OFFSET(M16,0,-Macro!$H$19)*Macro!$H$23,0) -> 0 | N21: =IF(ISNUMBER(OFFSET(N16,0,-Macro!$H$19))=TRUE,OFFSET(N16,0,-Macro!$H$19)*Macro!$H$23,0) -> 0 | O21: =IF(ISNUMBER(OFFSET(O16,0,-Macro!$H$19))=TRUE,OFFSET(O16,0,-Macro!$H$19)*Macro!$H$23,0) -> 0 | P21: =IF(ISNUMBER(OFFSET(P16,0,-Macro!$H$19))=TRUE,OFFSET(P16,0,-Macro!$H$19)*Macro!$H$23,0) -> 10000 | Q21: =IF(ISNUMBER(OFFSET(Q16,0,-Macro!$H$19))=TRUE,OFFSET(Q16,0,-Macro!$H$19)*Macro!$H$23,0) -> 10000 | R21: =IF(ISNUMBER(OFFSET(R16,0,-Macro!$H$19))=TRUE,OFFSET(R16,0,-Macro!$H$19)*Macro!$H$23,0) -> 10000 | S21: =IF(ISNUMBER(OFFSET(S16,0,-Macro!$H$19))=TRUE,OFFSET(S16,0,-Macro!$H$19)*Macro!$H$23,0) -> 12500 | T21: =IF(ISNUMBER(OFFSET(T16,0,-Macro!$H$19))=TRUE,OFFSET(T16,0,-Macro!$H$19)*Macro!$H$23,0) -> 12500 | ... AS21: =IF(ISNUMBER(OFFSET(AS16,0,-Macro!$H$19))=TRUE,OFFSET(AS16,0,-Macro!$H$19)*Macro!$H$23,0) -> 25000
C22: Expansion bookings | D22: =D20*D21 -> 0 | E22: =E20*E21 -> 0 | F22: =F20*F21 -> 0 | G22: =G20*G21 -> 0 | H22: f | I22: =I20*I21 -> 0 | J22: =J20*J21 -> 0 | K22: =K20*K21 -> 0 | L22: =L20*L21 -> 0 | M22: =M20*M21 -> 0 | N22: =N20*N21 -> 0 | O22: =O20*O21 -> 0 | P22: =P20*P21 -> 10000 | ... AS22: =AS20*AS21 -> 0
C24: Churn
C25: Churned customers | D25: 0 | E25: 0 | F25: 0 | G25: 0 | H25: 0 | I25: 0 | J25: 1 | K25: 1 | L25: 1 | M25: =ROUNDUP(IF(ISNUMBER(OFFSET(M15,0,-12))=TRUE,OFFSET(M15,0,-12)*Macro!$H$20,0),0) -> 0 | N25: =ROUNDUP(IF(ISNUMBER(OFFSET(N15,0,-12))=TRUE,OFFSET(N15,0,-12)*Macro!$H$20,0),0) -> 0 | O25: =ROUNDUP(IF(ISNUMBER(OFFSET(O15,0,-12))=TRUE,OFFSET(O15,0,-12)*Macro!$H$20,0),0) -> 0 | P25: =ROUNDUP(IF(ISNUMBER(OFFSET(P15,0,-12))=TRUE,OFFSET(P15,0,-12)*Macro!$H$20,0),0) -> 1 | Q25: =ROUNDUP(IF(ISNUMBER(OFFSET(Q15,0,-12))=TRUE,OFFSET(Q15,0,-12)*Macro!$H$20,0),0) -> 1 | R25: =ROUNDUP(IF(ISNUMBER(OFFSET(R15,0,-12))=TRUE,OFFSET(R15,0,-12)*Macro!$H$20,0),0) -> 1 | S25: =ROUNDUP(IF(ISNUMBER(OFFSET(S15,0,-12))=TRUE,OFFSET(S15,0,-12)*Macro!$H$20,0),0) -> 1 | T25: =ROUNDUP(IF(ISNUMBER(OFFSET(T15,0,-12))=TRUE,OFFSET(T15,0,-12)*Macro!$H$20,0),0) -> 1 | ... AS25: =ROUNDUP(IF(ISNUMBER(OFFSET(AS15,0,-12))=TRUE,OFFSET(AS15,0,-12)*Macro!$H$20,0),0) -> 0
C26: ACV of churned customers | D26: 0 | E26: 0 | F26: 0 | G26: 0 | H26: 0 | I26: 0 | J26: -20000 | K26: -20000 | L26: -20000 | M26: =-IF(ISNUMBER(OFFSET(M16,0,-12))=TRUE,OFFSET(M16,0,-12),0) -> 0 | N26: =-IF(ISNUMBER(OFFSET(N16,0,-12))=TRUE,OFFSET(N16,0,-12),0) -> 0 | O26: =-IF(ISNUMBER(OFFSET(O16,0,-12))=TRUE,OFFSET(O16,0,-12),0) -> 0 | P26: =-IF(ISNUMBER(OFFSET(P16,0,-12))=TRUE,OFFSET(P16,0,-12),0) -> -20000 | Q26: =-IF(ISNUMBER(OFFSET(Q16,0,-12))=TRUE,OFFSET(Q16,0,-12),0) -> -20000 | R26: =-IF(ISNUMBER(OFFSET(R16,0,-12))=TRUE,OFFSET(R16,0,-12),0) -> -20000 | S26: =-IF(ISNUMBER(OFFSET(S16,0,-12))=TRUE,OFFSET(S16,0,-12),0) -> -25000 | T26: =-IF(ISNUMBER(OFFSET(T16,0,-12))=TRUE,OFFSET(T16,0,-12),0) -> -25000 | ... AS26: =-IF(ISNUMBER(OFFSET(AS16,0,-12))=TRUE,OFFSET(AS16,0,-12),0) -> -50000
C27: Revenue churn | D27: =D25*D26 -> 0 | E27: =E25*E26 -> 0 | F27: =F25*F26 -> 0 | G27: =G25*G26 -> 0 | H27: =H25*H26 -> 0 | I27: =I25*I26 -> 0 | J27: =J25*J26 -> -20000 | K27: =K25*K26 -> -20000 | ... AS27: =AS25*AS26 -> 0
C29: Net new bookings | D29: 0 | E29: 0 | F29: 0 | G29: 0 | H29: 0 | I29: 0 | J29: =J17+J22+J27 -> 140000 | K29: =K17+K22+K27 -> 140000 | L29: =L17+L22+L27 -> 140000 | M29: =M17+M22+M27 -> #VALUE! | N29: =N17+N22+N27 -> #VALUE! | O29: =O17+O22+O27 -> #VALUE! | P29: =P17+P22+P27 -> #VALUE! | Q29: =Q17+Q22+Q27 -> #VALUE! | ... AS29: =AS17+AS22+AS27 -> #VALUE!
C30: # of Customers | D30: 1 | E30: =E15+D30-E25 -> 2 | F30: =F15+E30-F25 -> 3 | G30: =G15+F30-G25 -> 5 | H30: =H15+G30-H25 -> 7 | I30: =I15+H30-I25 -> 9 | J30: =J15+I30-J25 -> 12 | K30: =K15+J30-K25 -> 15 | L30: =L15+K30-L25 -> 18 | ... AS30: =AS15+AR30-AS25 -> #VALUE!
B32: Collections
C33: Gross New | J33: =OFFSET(J17,0,-Macro!$H$21) -> 50000 | K33: =OFFSET(K17,0,-Macro!$H$21) -> 160000 | L33: =OFFSET(L17,0,-Macro!$H$21) -> 160000 | M33: =OFFSET(M17,0,-Macro!$H$21) -> 160000 | N33: =OFFSET(N17,0,-Macro!$H$21) -> #VALUE! | O33: =OFFSET(O17,0,-Macro!$H$21) -> #VALUE! | P33: =OFFSET(P17,0,-Macro!$H$21) -> #VALUE! | Q33: =OFFSET(Q17,0,-Macro!$H$21) -> #VALUE! | ... AS33: =OFFSET(AS17,0,-Macro!$H$21) -> #VALUE!
C34: Retention | J34: =IFERROR(OFFSET(J17,0,-12)+OFFSET(J27,0,-12),0) -> 0 | K34: =IFERROR(OFFSET(K17,0,-12)+OFFSET(K27,0,-12),0) -> 0 | L34: =IFERROR(OFFSET(L17,0,-12)+OFFSET(L27,0,-12),0) -> 0 | M34: =IFERROR(OFFSET(M17,0,-12)+OFFSET(M27,0,-12),0) -> 0 | N34: =IFERROR(OFFSET(N17,0,-12)+OFFSET(N27,0,-12),0) -> 0 | O34: =IFERROR(OFFSET(O17,0,-12)+OFFSET(O27,0,-12),0) -> 0 | P34: =IFERROR(OFFSET(P17,0,-12)+OFFSET(P27,0,-12),0) -> 20000 | Q34: =IFERROR(OFFSET(Q17,0,-12)+OFFSET(Q27,0,-12),0) -> 20000 | ... AS34: =IFERROR(OFFSET(AS17,0,-12)+OFFSET(AS27,0,-12),0) -> 0
C35: Expansion | J35: =IFERROR(OFFSET(J22,0,-Macro!$H$21),0) -> 0 | K35: =IFERROR(OFFSET(K22,0,-Macro!$H$21),0) -> 0 | L35: =IFERROR(OFFSET(L22,0,-Macro!$H$21),0) -> 0 | M35: =IFERROR(OFFSET(M22,0,-Macro!$H$21),0) -> 0 | N35: =IFERROR(OFFSET(N22,0,-Macro!$H$21),0) -> 0 | O35: =IFERROR(OFFSET(O22,0,-Macro!$H$21),0) -> 0 | P35: =IFERROR(OFFSET(P22,0,-Macro!$H$21),0) -> 0 | Q35: =IFERROR(OFFSET(Q22,0,-Macro!$H$21),0) -> 10000 | ... AS35: =IFERROR(OFFSET(AS22,0,-Macro!$H$21),0) -> 0
C36: Collections | J36: =SUM(J33:J35) -> 50000 | K36: =SUM(K33:K35) -> 160000 | L36: =SUM(L33:L35) -> 160000 | M36: =SUM(M33:M35) -> 160000 | N36: =SUM(N33:N35) -> #VALUE! | O36: =SUM(O33:O35) -> #VALUE! | P36: =SUM(P33:P35) -> #VALUE! | Q36: =SUM(Q33:Q35) -> #VALUE! | ... AS36: =SUM(AS33:AS35) -> #VALUE!
B38: ARR
C39: ARR | D39: 20000 | E39: =D39+E44 -> 40000 | F39: =E39+F44 -> 60000 | G39: =F39+G44 -> 110000 | H39: =G39+H44 -> 160000 | I39: =H39+I44 -> 210000 | J39: =I39+J44 -> 350000 | K39: =J39+K44 -> 490000 | L39: =K39+L44 -> 630000 | ... AS39: =AR39+AS44 -> #VALUE!
C41: Gross New | D41: =D17 -> 20000 | E41: =E17 -> 20000 | F41: =F17 -> 20000 | G41: =G17 -> 50000 | H41: =H17 -> 50000 | I41: =I17 -> 50000 | J41: =J17 -> 160000 | K41: =K17 -> 160000 | ... AS41: =AS17 -> #VALUE!
C42: Expansion | D42: =D22 -> 0 | E42: =E22 -> 0 | F42: =F22 -> 0 | G42: =G22 -> 0 | H42: =H22 -> f | I42: =I22 -> 0 | J42: =J22 -> 0 | K42: =K22 -> 0 | ... AS42: =AS22 -> 0
C43: Churn | D43: =D27 -> 0 | E43: =E27 -> 0 | F43: =F27 -> 0 | G43: =G27 -> 0 | H43: =H27 -> 0 | I43: =I27 -> 0 | J43: =J27 -> -20000 | K43: =K27 -> -20000 | ... AS43: =AS27 -> 0
C44: Net new ARR | D44: =SUM(D41:D43) -> 20000 | E44: =SUM(E41:E43) -> 20000 | F44: =SUM(F41:F43) -> 20000 | G44: =SUM(G41:G43) -> 50000 | H44: =SUM(H41:H43) -> 50000 | I44: =SUM(I41:I43) -> 50000 | J44: =SUM(J41:J43) -> 140000 | K44: =SUM(K41:K43) -> 140000 | ... AS44: =SUM(AS41:AS43) -> #VALUE!

Sheet Team
A2: =Macro!A2 -> StartUp Co
B3: FY | D3: ='Top line'!D3 -> 2020 | J3: ='Top line'!J3 -> 2021 | V3: ='Top line'!V3 -> 2022 | AH3: ='Top line'!AH3 -> 2023
B4: Quarter | D4: ='Top line'!D4 -> 3 | G4: ='Top line'!G4 -> 4 | J4: ='Top line'!J4 -> 1 | M4: ='Top line'!M4 -> 2 | P4: ='Top line'!P4 -> 3 | S4: ='Top line'!S4 -> 4 | V4: ='Top line'!V4 -> 1 | Y4: ='Top line'!Y4 -> 2 | AB4: ='Top line'!AB4 -> 3 | AE4: ='Top line'!AE4 -> 4 | AH4: ='Top line'!AH4 -> 1 | AK4: ='Top line'!AK4 -> 2 | AN4: ='Top line'!AN4 -> 3 | AQ4: ='Top line'!AQ4 -> 4
B5: Month | D5: ='Top line'!D5 -> 43707 | E5: ='Top line'!E5 -> 43738 | F5: ='Top line'!F5 -> 43769 | G5: ='Top line'!G5 -> 43799 | H5: ='Top line'!H5 -> 43830 | I5: ='Top line'!I5 -> 43861 | J5: ='Top line'!J5 -> 43890 | K5: ='Top line'!K5 -> 43921 | ... AS5: ='Top line'!AS5 -> 44957
D6: Act | E6: Act | F6: Act | G6: Act | H6: Act | I6: Act | J6: Act | K6: Act | L6: Act | M6: Fcst | N6: Fcst | O6: Fcst | P6: Fcst | Q6: Fcst | R6: Fcst | S6: Fcst | T6: Fcst | U6: Fcst | V6: Fcst | W6: Fcst | X6: Fcst | Y6: Fcst | Z6: Fcst | AA6: Fcst | AB6: Fcst | AC6: Fcst | AD6: Fcst | AE6: Fcst | AF6: Fcst | AG6: Fcst | AH6: Fcst | AI6: Fcst | AJ6: Fcst | AK6: Fcst | AL6: Fcst | AM6: Fcst | AN6: Fcst | AO6: Fcst | AP6: Fcst | AQ6: Fcst | AR6: Fcst | AS6: Fcst
B8: Summary
B9: New hires | J9: =J30+J45+J73+J99+J112+J88 -> 0 | K9: =K30+K45+K73+K99+K112+K88 -> 0 | L9: =L30+L45+L73+L99+L112+L88 -> 6 | M9: =M30+M45+M73+M99+M112+M88 -> 1 | N9: =N30+N45+N73+N99+N112+N88 -> 1 | O9: =O30+O45+O73+O99+O112+O88 -> 2 | P9: =P30+P45+P73+P99+P112+P88 -> 2 | Q9: =Q30+Q45+Q73+Q99+Q112+Q88 -> 0 | ... AS9: =AS30+AS45+AS73+AS99+AS112+AS88 -> 0
B10: Headcount | J10: =J129+J144+J172+J198+J211+J187 -> 24 | K10: =K129+K144+K172+K198+K211+K187 -> 24 | L10: =L129+L144+L172+L198+L211+L187 -> 30 | M10: =M129+M144+M172+M198+M211+M187 -> 31 | N10: =N129+N144+N172+N198+N211+N187 -> 32 | O10: =O129+O144+O172+O198+O211+O187 -> 34 | P10: =P129+P144+P172+P198+P211+P187 -> 36 | Q10: =Q129+Q144+Q172+Q198+Q211+Q187 -> 36 | ... AS10: =AS129+AS144+AS172+AS198+AS211+AS187 -> 54
B11: Salaries | J11: =J228+J243+J271+J297+J310+J286 -> 303333.33 | K11: =K228+K243+K271+K297+K310+K286 -> 303333.33 | L11: =L228+L243+L271+L297+L310+L286 -> 378333.33 | M11: =M228+M243+M271+M297+M310+M286 -> 395000 | N11: =N228+N243+N271+N297+N310+N286 -> 407500 | O11: =O228+O243+O271+O297+O310+O286 -> 432500 | P11: =P228+P243+P271+P297+P310+P286 -> 445833.33 | Q11: =Q228+Q243+Q271+Q297+Q310+Q286 -> 445833.33 | ... AS11: =AS228+AS243+AS271+AS297+AS310+AS286 -> 644166.67
B12: Traveling personell | J12: =SUMPRODUCT(Team!J117:J128,Macro!$F$57:$F$68)+SUMPRODUCT(Macro!$F$71:$F$82,Team!J132:J143)+SUMPRODUCT(Team!J147:J171,Macro!$F$85:$F$109)+SUMPRODUCT(Team!J175:J186,Macro!$F$112:$F$123)+SUMPRODUCT(Macro!$F$126:$F$133,Team!J190:J197)+SUMPRODUCT(Team!J201:J210,Macro!$F$136:$F$145) -> 5 | K12: =SUMPRODUCT(Team!K117:K128,Macro!$F$57:$F$68)+SUMPRODUCT(Macro!$F$71:$F$82,Team!K132:K143)+SUMPRODUCT(Team!K147:K171,Macro!$F$85:$F$109)+SUMPRODUCT(Team!K175:K186,Macro!$F$112:$F$123)+SUMPRODUCT(Macro!$F$126:$F$133,Team!K190:K197)+SUMPRODUCT(Team!K201:K210,Macro!$F$136:$F$145) -> 5 | L12: =SUMPRODUCT(Team!L117:L128,Macro!$F$57:$F$68)+SUMPRODUCT(Macro!$F$71:$F$82,Team!L132:L143)+SUMPRODUCT(Team!L147:L171,Macro!$F$85:$F$109)+SUMPRODUCT(Team!L175:L186,Macro!$F$112:$F$123)+SUMPRODUCT(Macro!$F$126:$F$133,Team!L190:L197)+SUMPRODUCT(Team!L201:L210,Macro!$F$136:$F$145) -> 5 | M12: =SUMPRODUCT(Team!M117:M128,Macro!$F$57:$F$68)+SUMPRODUCT(Macro!$F$71:$F$82,Team!M132:M143)+SUMPRODUCT(Team!M147:M171,Macro!$F$85:$F$109)+SUMPRODUCT(Team!M175:M186,Macro!$F$112:$F$123)+SUMPRODUCT(Macro!$F$126:$F$133,Team!M190:M197)+SUMPRODUCT(Team!M201:M210,Macro!$F$136:$F$145) -> 6 | N12: =SUMPRODUCT(Team!N117:N128,Macro!$F$57:$F$68)+SUMPRODUCT(Macro!$F$71:$F$82,Team!N132:N143)+SUMPRODUCT(Team!N147:N171,Macro!$F$85:$F$109)+SUMPRODUCT(Team!N175:N186,Macro!$F$112:$F$123)+SUMPRODUCT(Macro!$F$126:$F$133,Team!N190:N197)+SUMPRODUCT(Team!N201:N210,Macro!$F$136:$F$145) -> 6 | O12: =SUMPRODUCT(Team!O117:O128,Macro!$F$57:$F$68)+SUMPRODUCT(Macro!$F$71:$F$82,Team!O132:O143)+SUMPRODUCT(Team!O147:O171,Macro!$F$85:$F$109)+SUMPRODUCT(Team!O175:O186,Macro!$F$112:$F$123)+SUMPRODUCT(Macro!$F$126:$F$133,Team!O190:O197)+SUMPRODUCT(Team!O201:O210,Macro!$F$136:$F$145) -> 6 | P12: =SUMPRODUCT(Team!P117:P128,Macro!$F$57:$F$68)+SUMPRODUCT(Macro!$F$71:$F$82,Team!P132:P143)+SUMPRODUCT(Team!P147:P171,Macro!$F$85:$F$109)+SUMPRODUCT(Team!P175:P186,Macro!$F$112:$F$123)+SUMPRODUCT(Macro!$F$126:$F$133,Team!P190:P197)+SUMPRODUCT(Team!P201:P210,Macro!$F$136:$F$145) -> 8 | Q12: =SUMPRODUCT(Team!Q117:Q128,Macro!$F$57:$F$68)+SUMPRODUCT(Macro!$F$71:$F$82,Team!Q132:Q143)+SUMPRODUCT(Team!Q147:Q171,Macro!$F$85:$F$109)+SUMPRODUCT(Team!Q175:Q186,Macro!$F$112:$F$123)+SUMPRODUCT(Macro!$F$126:$F$133,Team!Q190:Q197)+SUMPRODUCT(Team!Q201:Q210,Macro!$F$136:$F$145) -> 8 | ... AS12: =SUMPRODUCT(Team!AS117:AS128,Macro!$F$57:$F$68)+SUMPRODUCT(Macro!$F$71:$F$82,Team!AS132:AS143)+SUMPRODUCT(Team!AS147:AS171,Macro!$F$85:$F$109)+SUMPRODUCT(Team!AS175:AS186,Macro!$F$112:$F$123)+SUMPRODUCT(Macro!$F$126:$F$133,Team!AS190:AS197)+SUMPRODUCT(Team!AS201:AS210,Macro!$F$136:$F$145) -> 17
B13: Non-travelers | J13: =J10-J12 -> 19 | K13: =K10-K12 -> 19 | L13: =L10-L12 -> 25 | M13: =M10-M12 -> 25 | N13: =N10-N12 -> 26 | O13: =O10-O12 -> 28 | P13: =P10-P12 -> 28 | Q13: =Q10-Q12 -> 28 | ... AS13: =AS10-AS12 -> 37
B15: Headcount Changes
B17: Sales
C18: =Macro!B57 -> CRO | E18: =E117-D117 -> 0 | F18: =F117-E117 -> 0 | G18: =G117-F117 -> 0 | H18: =H117-G117 -> 0 | I18: =I117-H117 -> 0 | J18: =J117-I117 -> 0 | K18: =K117-J117 -> 0 | L18: =L117-K117 -> 0 | ... AS18: =AS117-AR117 -> 0
C19: =Macro!B58 -> AE | E19: =E118-D118 -> 0 | F19: =F118-E118 -> 0 | G19: =G118-F118 -> 0 | H19: =H118-G118 -> 0 | I19: =I118-H118 -> 0 | J19: =J118-I118 -> 0 | K19: =K118-J118 -> 0 | L19: =L118-K118 -> 0 | ... AS19: =AS118-AR118 -> 0
C20: =Macro!B59 -> AE manager | E20: =E119-D119 -> 0 | F20: =F119-E119 -> 0 | G20: =G119-F119 -> 0 | H20: =H119-G119 -> 0 | I20: =I119-H119 -> 0 | J20: =J119-I119 -> 0 | K20: =K119-J119 -> 0 | L20: =L119-K119 -> 0 | ... AS20: =AS119-AR119 -> 0
C21: =Macro!B60 -> SE | E21: =E120-D120 -> 0 | F21: =F120-E120 -> 0 | G21: =G120-F120 -> 0 | H21: =H120-G120 -> 0 | I21: =I120-H120 -> 0 | J21: =J120-I120 -> 0 | K21: =K120-J120 -> 0 | L21: =L120-K120 -> 0 | ... AS21: =AS120-AR120 -> 0
C22: =Macro!B61 -> SE manager | E22: =E121-D121 -> 0 | F22: =F121-E121 -> 0 | G22: =G121-F121 -> 0 | H22: =H121-G121 -> 0 | I22: =I121-H121 -> 0 | J22: =J121-I121 -> 0 | K22: =K121-J121 -> 0 | L22: =L121-K121 -> 0 | ... AS22: =AS121-AR121 -> 0
C23: =Macro!B62 -> Sales Ops | E23: =E122-D122 -> 0 | F23: =F122-E122 -> 0 | G23: =G122-F122 -> 0 | H23: =H122-G122 -> 0 | I23: =I122-H122 -> 0 | J23: =J122-I122 -> 0 | K23: =K122-J122 -> 0 | L23: =L122-K122 -> 0 | ... AS23: =AS122-AR122 -> 0
C24: =Macro!B63 -> [XX] | E24: =E123-D123 -> 0 | F24: =F123-E123 -> 0 | G24: =G123-F123 -> 0 | H24: =H123-G123 -> 0 | I24: =I123-H123 -> 0 | J24: =J123-I123 -> 0 | K24: =K123-J123 -> 0 | L24: =L123-K123 -> 0 | ... AS24: =AS123-AR123 -> 0
C25: =Macro!B64 -> [XX] | E25: =E124-D124 -> 0 | F25: =F124-E124 -> 0 | G25: =G124-F124 -> 0 | H25: =H124-G124 -> 0 | I25: =I124-H124 -> 0 | J25: =J124-I124 -> 0 | K25: =K124-J124 -> 0 | L25: =L124-K124 -> 0 | ... AS25: =AS124-AR124 -> 0
C26: =Macro!B65 -> [XX] | E26: =E125-D125 -> 0 | F26: =F125-E125 -> 0 | G26: =G125-F125 -> 0 | H26: =H125-G125 -> 0 | I26: =I125-H125 -> 0 | J26: =J125-I125 -> 0 | K26: =K125-J125 -> 0 | L26: =L125-K125 -> 0 | ... AS26: =AS125-AR125 -> 0
C27: =Macro!B66 -> [XX] | E27: =E126-D126 -> 0 | F27: =F126-E126 -> 0 | G27: =G126-F126 -> 0 | H27: =H126-G126 -> 0 | I27: =I126-H126 -> 0 | J27: =J126-I126 -> 0 | K27: =K126-J126 -> 0 | L27: =L126-K126 -> 0 | ... AS27: =AS126-AR126 -> 0
C28: =Macro!B67 -> [XX] | E28: =E127-D127 -> 0 | F28: =F127-E127 -> 0 | G28: =G127-F127 -> 0 | H28: =H127-G127 -> 0 | I28: =I127-H127 -> 0 | J28: =J127-I127 -> 0 | K28: =K127-J127 -> 0 | L28: =L127-K127 -> 0 | ... AS28: =AS127-AR127 -> 0
C29: =Macro!B68 -> [XX] | E29: =E128-D128 -> 0 | F29: =F128-E128 -> 0 | G29: =G128-F128 -> 0 | H29: =H128-G128 -> 0 | I29: =I128-H128 -> 0 | J29: =J128-I128 -> 0 | K29: =K128-J128 -> 0 | L29: =L128-K128 -> 0 | ... AS29: =AS128-AR128 -> 0
C30: Total | E30: =SUM(E18:E29) -> 0 | F30: =SUM(F18:F29) -> 0 | G30: =SUM(G18:G29) -> 0 | H30: =SUM(H18:H29) -> 0 | I30: =SUM(I18:I29) -> 0 | J30: =SUM(J18:J29) -> 0 | K30: =SUM(K18:K29) -> 0 | L30: =SUM(L18:L29) -> 0 | ... AS30: =SUM(AS18:AS29) -> 0
B32: Marketing
C33: =Macro!B71 -> CMO | E33: =E132-D132 -> 0 | F33: =F132-E132 -> 0 | G33: =G132-F132 -> 0 | H33: =H132-G132 -> 0 | I33: =I132-H132 -> 0 | J33: =J132-I132 -> 0 | K33: =K132-J132 -> 0 | L33: =L132-K132 -> 0 | ... AS33: =AS132-AR132 -> 0
C34: =Macro!B72 -> Director of Demand | E34: =E133-D133 -> 0 | F34: =F133-E133 -> 0 | G34: =G133-F133 -> 0 | H34: =H133-G133 -> 0 | I34: =I133-H133 -> 0 | J34: =J133-I133 -> 0 | K34: =K133-J133 -> 0 | L34: =L133-K133 -> 0 | ... AS34: =AS133-AR133 -> 0
C35: =Macro!B73 -> SDR | E35: =E134-D134 -> 0 | F35: =F134-E134 -> 0 | G35: =G134-F134 -> 0 | H35: =H134-G134 -> 0 | I35: =I134-H134 -> 0 | J35: =J134-I134 -> 0 | K35: =K134-J134 -> 0 | L35: =L134-K134 -> 0 | ... AS35: =AS134-AR134 -> 0
C36: =Macro!B74 -> Creative | E36: =E135-D135 -> 0 | F36: =F135-E135 -> 0 | G36: =G135-F135 -> 0 | H36: =H135-G135 -> 0 | I36: =I135-H135 -> 0 | J36: =J135-I135 -> 0 | K36: =K135-J135 -> 0 | L36: =L135-K135 -> 0 | ... AS36: =AS135-AR135 -> 0
C37: =Macro!B75 -> PMM / VP Marketing | E37: =E136-D136 -> 0 | F37: =F136-E136 -> 0 | G37: =G136-F136 -> 0 | H37: =H136-G136 -> 0 | I37: =I136-H136 -> 0 | J37: =J136-I136 -> 0 | K37: =K136-J136 -> 0 | L37: =L136-K136 -> 1 | ... AS37: =AS136-AR136 -> 0
C38: =Macro!B76 -> Field | E38: =E137-D137 -> 0 | F38: =F137-E137 -> 0 | G38: =G137-F137 -> 0 | H38: =H137-G137 -> 0 | I38: =I137-H137 -> 0 | J38: =J137-I137 -> 0 | K38: =K137-J137 -> 0 | L38: =L137-K137 -> 0 | ... AS38: =AS137-AR137 -> 0
C39: =Macro!B77 -> [XX] | E39: =E138-D138 -> 0 | F39: =F138-E138 -> 0 | G39: =G138-F138 -> 0 | H39: =H138-G138 -> 0 | I39: =I138-H138 -> 0 | J39: =J138-I138 -> 0 | K39: =K138-J138 -> 0 | L39: =L138-K138 -> 0 | ... AS39: =AS138-AR138 -> 0
C40: =Macro!B78 -> [XX] | E40: =E139-D139 -> 0 | F40: =F139-E139 -> 0 | G40: =G139-F139 -> 0 | H40: =H139-G139 -> 0 | I40: =I139-H139 -> 0 | J40: =J139-I139 -> 0 | K40: =K139-J139 -> 0 | L40: =L139-K139 -> 0 | ... AS40: =AS139-AR139 -> 0
C41: =Macro!B79 -> [XX] | E41: =E140-D140 -> 0 | F41: =F140-E140 -> 0 | G41: =G140-F140 -> 0 | H41: =H140-G140 -> 0 | I41: =I140-H140 -> 0 | J41: =J140-I140 -> 0 | K41: =K140-J140 -> 0 | L41: =L140-K140 -> 0 | ... AS41: =AS140-AR140 -> 0
C42: =Macro!B80 -> [XX] | E42: =E141-D141 -> 0 | F42: =F141-E141 -> 0 | G42: =G141-F141 -> 0 | H42: =H141-G141 -> 0 | I42: =I141-H141 -> 0 | J42: =J141-I141 -> 0 | K42: =K141-J141 -> 0 | L42: =L141-K141 -> 0 | ... AS42: =AS141-AR141 -> 0
C43: =Macro!B81 -> [XX] | E43: =E142-D142 -> 0 | F43: =F142-E142 -> 0 | G43: =G142-F142 -> 0 | H43: =H142-G142 -> 0 | I43: =I142-H142 -> 0 | J43: =J142-I142 -> 0 | K43: =K142-J142 -> 0 | L43: =L142-K142 -> 0 | ... AS43: =AS142-AR142 -> 0
C44: =Macro!B82 -> [XX] | E44: =E143-D143 -> 0 | F44: =F143-E143 -> 0 | G44: =G143-F143 -> 0 | H44: =H143-G143 -> 0 | I44: =I143-H143 -> 0 | J44: =J143-I143 -> 0 | K44: =K143-J143 -> 0 | L44: =L143-K143 -> 0 | ... AS44: =AS143-AR143 -> 0
C45: Total | E45: =SUM(E33:E44) -> 0 | F45: =SUM(F33:F44) -> 0 | G45: =SUM(G33:G44) -> 0 | H45: =SUM(H33:H44) -> 0 | I45: =SUM(I33:I44) -> 0 | J45: =SUM(J33:J44) -> 0 | K45: =SUM(K33:K44) -> 0 | L45: =SUM(L33:L44) -> 1 | ... AS45: =SUM(AS33:AS44) -> 0
B47: Engineering (Excluding Outsource Team)
C48: =Macro!B85 -> Chief Architect | E48: =E147-D147 -> 0 | F48: =F147-E147 -> 0 | G48: =G147-F147 -> 0 | H48: =H147-G147 -> 0 | I48: =I147-H147 -> 0 | J48: =J147-I147 -> 0 | K48: =K147-J147 -> 0 | L48: =L147-K147 -> 0 | ... AS48: =AS147-AR147 -> 0
C49: =Macro!B86 -> VP Engineering | E49: =E148-D148 -> 0 | F49: =F148-E148 -> 0 | G49: =G148-F148 -> 0 | H49: =H148-G148 -> 0 | I49: =I148-H148 -> 0 | J49: =J148-I148 -> 0 | K49: =K148-J148 -> 0 | L49: =L148-K148 -> 0 | ... AS49: =AS148-AR148 -> 0
C50: =Macro!B87 -> Founding Frontend Engineer | E50: =E149-D149 -> 0 | F50: =F149-E149 -> 0 | G50: =G149-F149 -> 0 | H50: =H149-G149 -> 0 | I50: =I149-H149 -> 0 | J50: =J149-I149 -> 0 | K50: =K149-J149 -> 0 | L50: =L149-K149 -> 0 | ... AS50: =AS149-AR149 -> 0
C51: =Macro!B88 -> Founding Backend Engineer | E51: =E150-D150 -> 0 | F51: =F150-E150 -> 0 | G51: =G150-F150 -> 0 | H51: =H150-G150 -> 0 | I51: =I150-H150 -> 0 | J51: =J150-I150 -> 0 | K51: =K150-J150 -> 0 | L51: =L150-K150 -> 0 | ... AS51: =AS150-AR150 -> 0
C52: =Macro!B89 -> Founding API Engineer | E52: =E151-D151 -> 0 | F52: =F151-E151 -> 0 | G52: =G151-F151 -> 0 | H52: =H151-G151 -> 0 | I52: =I151-H151 -> 0 | J52: =J151-I151 -> 0 | K52: =K151-J151 -> 0 | L52: =L151-K151 -> 0 | ... AS52: =AS151-AR151 -> 0
C53: =Macro!B90 -> Platform Engineer | E53: =E152-D152 -> 0 | F53: =F152-E152 -> 0 | G53: =G152-F152 -> 0 | H53: =H152-G152 -> 0 | I53: =I152-H152 -> 0 | J53: =J152-I152 -> 0 | K53: =K152-J152 -> 0 | L53: =L152-K152 -> 0 | ... AS53: =AS152-AR152 -> 0
C54: =Macro!B91 -> Head of Analytics | E54: =E153-D153 -> 0 | F54: =F153-E153 -> 0 | G54: =G153-F153 -> 0 | H54: =H153-G153 -> 0 | I54: =I153-H153 -> 0 | J54: =J153-I153 -> 0 | K54: =K153-J153 -> 0 | L54: =L153-K153 -> 0 | ... AS54: =AS153-AR153 -> 0
C55: =Macro!B92 -> Quality Assurance Lead | E55: =E154-D154 -> 0 | F55: =F154-E154 -> 0 | G55: =G154-F154 -> 0 | H55: =H154-G154 -> 0 | I55: =I154-H154 -> 0 | J55: =J154-I154 -> 0 | K55: =K154-J154 -> 0 | L55: =L154-K154 -> 0 | ... AS55: =AS154-AR154 -> 0
C56: =Macro!B93 -> Frontend Engr | E56: =E155-D155 -> 0 | F56: =F155-E155 -> 0 | G56: =G155-F155 -> 0 | H56: =H155-G155 -> 0 | I56: =I155-H155 -> 0 | J56: =J155-I155 -> 0 | K56: =K155-J155 -> 0 | L56: =L155-K155 -> 0 | ... AS56: =AS155-AR155 -> 0
C57: =Macro!B94 -> DevOps Engineer | E57: =E156-D156 -> 0 | F57: =F156-E156 -> 0 | G57: =G156-F156 -> 0 | H57: =H156-G156 -> 0 | I57: =I156-H156 -> 0 | J57: =J156-I156 -> 0 | K57: =K156-J156 -> 0 | L57: =L156-K156 -> 0 | ... AS57: =AS156-AR156 -> 0
C58: =Macro!B95 -> MobileApps Engineer | E58: =E157-D157 -> 0 | F58: =F157-E157 -> 0 | G58: =G157-F157 -> 0 | H58: =H157-G157 -> 0 | I58: =I157-H157 -> 0 | J58: =J157-I157 -> 0 | K58: =K157-J157 -> 0 | L58: =L157-K157 -> 0 | ... AS58: =AS157-AR157 -> 0
C59: =Macro!B96 -> API Engineer | E59: =E158-D158 -> 0 | F59: =F158-E158 -> 0 | G59: =G158-F158 -> 0 | H59: =H158-G158 -> 0 | I59: =I158-H158 -> 0 | J59: =J158-I158 -> 0 | K59: =K158-J158 -> 0 | L59: =L158-K158 -> 1 | ... AS59: =AS158-AR158 -> 0
... C72: =Macro!B109 -> [XX] | E72: =E171-D171 -> 0 | F72: =F171-E171 -> 0 | G72: =G171-F171 -> 0 | H72: =H171-G171 -> 0 | I72: =I171-H171 -> 0 | J72: =J171-I171 -> 0 | K72: =K171-J171 -> 0 | L72: =L171-K171 -> 0 | ... AS72: =AS171-AR171 -> 0
C73: Total | E73: =SUM(E48:E72) -> 0 | F73: =SUM(F48:F72) -> 0 | G73: =SUM(G48:G72) -> 0 | H73: =SUM(H48:H72) -> 0 | I73: =SUM(I48:I72) -> 0 | J73: =SUM(J48:J72) -> 0 | K73: =SUM(K48:K72) -> 0 | L73: =SUM(L48:L72) -> 5 | ... AS73: =SUM(AS48:AS72) -> 0
B75: Product
C76: =Macro!B112 -> Founding Product Designer | E76: =E175-D175 -> 0 | F76: =F175-E175 -> 0 | G76: =G175-F175 -> 0 | H76: =H175-G175 -> 0 | I76: =I175-H175 -> 0 | J76: =J175-I175 -> 0 | K76: =K175-J175 -> 0 | L76: =L175-K175 -> 0 | ... AS76: =AS175-AR175 -> 0
C77: =Macro!B113 -> Product Manager | E77: =E176-D176 -> 0 | F77: =F176-E176 -> 0 | G77: =G176-F176 -> 0 | H77: =H176-G176 -> 0 | I77: =I176-H176 -> 0 | J77: =J176-I176 -> 0 | K77: =K176-J176 -> 0 | L77: =L176-K176 -> 0 | ... AS77: =AS176-AR176 -> 0
C78: =Macro!B114 -> Tech Writer | E78: =E177-D177 -> 0 | F78: =F177-E177 -> 0 | G78: =G177-F177 -> 0 | H78: =H177-G177 -> 0 | I78: =I177-H177 -> 0 | J78: =J177-I177 -> 0 | K78: =K177-J177 -> 0 | L78: =L177-K177 -> 0 | ... AS78: =AS177-AR177 -> 0
C79: =Macro!B115 -> [XX] | E79: =E178-D178 -> 0 | F79: =F178-E178 -> 0 | G79: =G178-F178 -> 0 | H79: =H178-G178 -> 0 | I79: =I178-H178 -> 0 | J79: =J178-I178 -> 0 | K79: =K178-J178 -> 0 | L79: =L178-K178 -> 0 | ... AS79: =AS178-AR178 -> 0
C80: =Macro!B116 -> [XX] | E80: =E179-D179 -> 0 | F80: =F179-E179 -> 0 | G80: =G179-F179 -> 0 | H80: =H179-G179 -> 0 | I80: =I179-H179 -> 0 | J80: =J179-I179 -> 0 | K80: =K179-J179 -> 0 | L80: =L179-K179 -> 0 | ... AS80: =AS179-AR179 -> 0
C81: =Macro!B117 -> [XX] | E81: =E180-D180 -> 0 | F81: =F180-E180 -> 0 | G81: =G180-F180 -> 0 | H81: =H180-G180 -> 0 | I81: =I180-H180 -> 0 | J81: =J180-I180 -> 0 | K81: =K180-J180 -> 0 | L81: =L180-K180 -> 0 | ... AS81: =AS180-AR180 -> 0
C82: =Macro!B118 -> [XX] | E82: =E181-D181 -> 0 | F82: =F181-E181 -> 0 | G82: =G181-F181 -> 0 | H82: =H181-G181 -> 0 | I82: =I181-H181 -> 0 | J82: =J181-I181 -> 0 | K82: =K181-J181 -> 0 | L82: =L181-K181 -> 0 | ... AS82: =AS181-AR181 -> 0
C83: =Macro!B119 -> [XX] | E83: =E182-D182 -> 0 | F83: =F182-E182 -> 0 | G83: =G182-F182 -> 0 | H83: =H182-G182 -> 0 | I83: =I182-H182 -> 0 | J83: =J182-I182 -> 0 | K83: =K182-J182 -> 0 | L83: =L182-K182 -> 0 | ... AS83: =AS182-AR182 -> 0
C84: =Macro!B120 -> [XX] | E84: =E183-D183 -> 0 | F84: =F183-E183 -> 0 | G84: =G183-F183 -> 0 | H84: =H183-G183 -> 0 | I84: =I183-H183 -> 0 | J84: =J183-I183 -> 0 | K84: =K183-J183 -> 0 | L84: =L183-K183 -> 0 | ... AS84: =AS183-AR183 -> 0
C85: =Macro!B121 -> [XX] | E85: =E184-D184 -> 0 | F85: =F184-E184 -> 0 | G85: =G184-F184 -> 0 | H85: =H184-G184 -> 0 | I85: =I184-H184 -> 0 | J85: =J184-I184 -> 0 | K85: =K184-J184 -> 0 | L85: =L184-K184 -> 0 | ... AS85: =AS184-AR184 -> 0
C86: =Macro!B122 -> [XX] | E86: =E185-D185 -> 0 | F86: =F185-E185 -> 0 | G86: =G185-F185 -> 0 | H86: =H185-G185 -> 0 | I86: =I185-H185 -> 0 | J86: =J185-I185 -> 0 | K86: =K185-J185 -> 0 | L86: =L185-K185 -> 0 | ... AS86: =AS185-AR185 -> 0
C87: =Macro!B123 -> [XX] | E87: =E186-D186 -> 0 | F87: =F186-E186 -> 0 | G87: =G186-F186 -> 0 | H87: =H186-G186 -> 0 | I87: =I186-H186 -> 0 | J87: =J186-I186 -> 0 | K87: =K186-J186 -> 0 | L87: =L186-K186 -> 0 | ... AS87: =AS186-AR186 -> 0
C88: Total | E88: =SUM(E76:E87) -> 0 | F88: =SUM(F76:F87) -> 0 | G88: =SUM(G76:G87) -> 0 | H88: =SUM(H76:H87) -> 0 | I88: =SUM(I76:I87) -> 0 | J88: =SUM(J76:J87) -> 0 | K88: =SUM(K76:K87) -> 0 | L88: =SUM(L76:L87) -> 0 | ... AS88: =SUM(AS76:AS87) -> 0
B90: Customer Success
C91: =Macro!B126 -> VP | E91: =E190-D190 -> 0 | F91: =F190-E190 -> 0 | G91: =G190-F190 -> 0 | H91: =H190-G190 -> 0 | I91: =I190-H190 -> 0 | J91: =J190-I190 -> 0 | K91: =K190-J190 -> 0 | L91: =L190-K190 -> 0 | ... AS91: =AS190-AR190 -> 0
C92: =Macro!B127 -> CS Director | E92: =E191-D191 -> 0 | F92: =F191-E191 -> 0 | G92: =G191-F191 -> 0 | H92: =H191-G191 -> 0 | I92: =I191-H191 -> 0 | J92: =J191-I191 -> 0 | K92: =K191-J191 -> 0 | L92: =L191-K191 -> 0 | ... AS92: =AS191-AR191 -> 0
C93: =Macro!B128 -> CS Engineer | E93: =E192-D192 -> 0 | F93: =F192-E192 -> 0 | G93: =G192-F192 -> 0 | H93: =H192-G192 -> 0 | I93: =I192-H192 -> 0 | J93: =J192-I192 -> 0 | K93: =K192-J192 -> 0 | L93: =L192-K192 -> 0 | ... AS93: =AS192-AR192 -> 0
C94: =Macro!B129 -> [XX] | E94: =E193-D193 -> 0 | F94: =F193-E193 -> 0 | G94: =G193-F193 -> 0 | H94: =H193-G193 -> 0 | I94: =I193-H193 -> 0 | J94: =J193-I193 -> 0 | K94: =K193-J193 -> 0 | L94: =L193-K193 -> 0 | ... AS94: =AS193-AR193 -> 0
C95: =Macro!B130 -> [XX] | E95: =E194-D194 -> 0 | F95: =F194-E194 -> 0 | G95: =G194-F194 -> 0 | H95: =H194-G194 -> 0 | I95: =I194-H194 -> 0 | J95: =J194-I194 -> 0 | K95: =K194-J194 -> 0 | L95: =L194-K194 -> 0 | ... AS95: =AS194-AR194 -> 0
C96: =Macro!B131 -> [XX] | E96: =E195-D195 -> 0 | F96: =F195-E195 -> 0 | G96: =G195-F195 -> 0 | H96: =H195-G195 -> 0 | I96: =I195-H195 -> 0 | J96: =J195-I195 -> 0 | K96: =K195-J195 -> 0 | L96: =L195-K195 -> 0 | ... AS96: =AS195-AR195 -> 0
C97: =Macro!B132 -> [XX] | E97: =E196-D196 -> 0 | F97: =F196-E196 -> 0 | G97: =G196-F196 -> 0 | H97: =H196-G196 -> 0 | I97: =I196-H196 -> 0 | J97: =J196-I196 -> 0 | K97: =K196-J196 -> 0 | L97: =L196-K196 -> 0 | ... AS97: =AS196-AR196 -> 0
C98: =Macro!B133 -> [XX] | E98: =E197-D197 -> 0 | F98: =F197-E197 -> 0 | G98: =G197-F197 -> 0 | H98: =H197-G197 -> 0 | I98: =I197-H197 -> 0 | J98: =J197-I197 -> 0 | K98: =K197-J197 -> 0 | L98: =L197-K197 -> 0 | ... AS98: =AS197-AR197 -> 0
C99: Total | E99: =SUM(E91:E98) -> 0 | F99: =SUM(F91:F98) -> 0 | G99: =SUM(G91:G98) -> 0 | H99: =SUM(H91:H98) -> 0 | I99: =SUM(I91:I98) -> 0 | J99: =SUM(J91:J98) -> 0 | K99: =SUM(K91:K98) -> 0 | L99: =SUM(L91:L98) -> 0 | ... AS99: =SUM(AS91:AS98) -> 0
B101: G&A
C102: =Macro!B136 -> CEO | E102: =E201-D201 -> 0 | F102: =F201-E201 -> 0 | G102: =G201-F201 -> 0 | H102: =H201-G201 -> 0 | I102: =I201-H201 -> 0 | J102: =J201-I201 -> 0 | K102: =K201-J201 -> 0 | L102: =L201-K201 -> 0 | ... AS102: =AS201-AR201 -> 0
C103: =Macro!B137 -> COO | E103: =E202-D202 -> 0 | F103: =F202-E202 -> 0 | G103: =G202-F202 -> 0 | H103: =H202-G202 -> 0 | I103: =I202-H202 -> 0 | J103: =J202-I202 -> 0 | K103: =K202-J202 -> 0 | L103: =L202-K202 -> 0 | ... AS103: =AS202-AR202 -> 0
C104: =Macro!B138 -> Head of Talent / HR | E104: =E203-D203 -> 0 | F104: =F203-E203 -> 0 | G104: =G203-F203 -> 0 | H104: =H203-G203 -> 0 | I104: =I203-H203 -> 0 | J104: =J203-I203 -> 0 | K104: =K203-J203 -> 0 | L104: =L203-K203 -> 0 | ... AS104: =AS203-AR203 -> 0
C105: =Macro!B139 -> Office Admin / EA | E105: =E204-D204 -> 0 | F105: =F204-E204 -> 0 | G105: =G204-F204 -> 0 | H105: =H204-G204 -> 0 | I105: =I204-H204 -> 0 | J105: =J204-I204 -> 0 | K105: =K204-J204 -> 0 | L105: =L204-K204 -> 0 | ... AS105: =AS204-AR204 -> 0
C106: =Macro!B140 -> Finance Director | E106: =E205-D205 -> 0 | F106: =F205-E205 -> 0 | G106: =G205-F205 -> 0 | H106: =H205-G205 -> 0 | I106: =I205-H205 -> 0 | J106: =J205-I205 -> 0 | K106: =K205-J205 -> 0 | L106: =L205-K205 -> 0 | ... AS106: =AS205-AR205 -> 0
C107: =Macro!B141 -> [XX] | E107: =E206-D206 -> 0 | F107: =F206-E206 -> 0 | G107: =G206-F206 -> 0 | H107: =H206-G206 -> 0 | I107: =I206-H206 -> 0 | J107: =J206-I206 -> 0 | K107: =K206-J206 -> 0 | L107: =L206-K206 -> 0 | ... AS107: =AS206-AR206 -> 0
C108: =Macro!B142 -> [XX] | E108: =E207-D207 -> 0 | F108: =F207-E207 -> 0 | G108: =G207-F207 -> 0 | H108: =H207-G207 -> 0 | I108: =I207-H207 -> 0 | J108: =J207-I207 -> 0 | K108: =K207-J207 -> 0 | L108: =L207-K207 -> 0 | ... AS108: =AS207-AR207 -> 0
C109: =Macro!B143 -> [XX] | E109: =E208-D208 -> 0 | F109: =F208-E208 -> 0 | G109: =G208-F208 -> 0 | H109: =H208-G208 -> 0 | I109: =I208-H208 -> 0 | J109: =J208-I208 -> 0 | K109: =K208-J208 -> 0 | L109: =L208-K208 -> 0 | ... AS109: =AS208-AR208 -> 0
C110: =Macro!B144 -> [XX] | E110: =E209-D209 -> 0 | F110: =F209-E209 -> 0 | G110: =G209-F209 -> 0 | H110: =H209-G209 -> 0 | I110: =I209-H209 -> 0 | J110: =J209-I209 -> 0 | K110: =K209-J209 -> 0 | L110: =L209-K209 -> 0 | ... AS110: =AS209-AR209 -> 0
C111: =Macro!B145 -> [XX] | E111: =E210-D210 -> 0 | F111: =F210-E210 -> 0 | G111: =G210-F210 -> 0 | H111: =H210-G210 -> 0 | I111: =I210-H210 -> 0 | J111: =J210-I210 -> 0 | K111: =K210-J210 -> 0 | L111: =L210-K210 -> 0 | ... AS111: =AS210-AR210 -> 0
C112: Total | E112: =SUM(E102:E111) -> 0 | F112: =SUM(F102:F111) -> 0 | G112: =SUM(G102:G111) -> 0 | H112: =SUM(H102:H111) -> 0 | I112: =SUM(I102:I111) -> 0 | J112: =SUM(J102:J111) -> 0 | K112: =SUM(K102:K111) -> 0 | L112: =SUM(L102:L111) -> 0 | ... AS112: =SUM(AS102:AS111) -> 0
B114: Headcount
B116: Sales
C117: =Macro!B57 -> CRO | D117: 0 | E117: 0 | F117: 0 | G117: 0 | H117: 0 | I117: 0 | J117: 0 | K117: 0 | L117: 0 | M117: 1 | N117: 1 | O117: 1 | P117: 1 | Q117: 1 | R117: 1 | S117: 1 | T117: 1 | U117: 1 | V117: 1 | W117: 1 | X117: 1 | Y117: 1 | Z117: 1 | AA117: 1 | AB117: 1 | AC117: 1 | AD117: 1 | AE117: 1 | AF117: 1 | AG117: 1 | AH117: 1 | AI117: 1 | AJ117: 1 | AK117: 1 | AL117: 1 | AM117: 1 | AN117: 1 | AO117: 1 | AP117: 1 | AQ117: 1 | AR117: 1 | AS117: 1
C118: =Macro!B58 -> AE | D118: 2 | E118: 2 | F118: 2 | G118: 2 | H118: 2 | I118: 2 | J118: 2 | K118: 2 | L118: 2 | M118: 2 | N118: 2 | O118: 2 | P118: 3 | Q118: 3 | R118: 3 | S118: 3 | T118: 3 | U118: 3 | V118: 4 | W118: 4 | X118: 4 | Y118: 4 | Z118: 4 | AA118: 4 | AB118: 5 | AC118: 5 | AD118: 5 | AE118: 5 | AF118: 5 | AG118: 5 | AH118: 6 | AI118: 6 | AJ118: 6 | AK118: 6 | AL118: 6 | AM118: 6 | AN118: 7 | AO118: 7 | AP118: 7 | AQ118: 7 | AR118: 7 | AS118: 7
C119: =Macro!B59 -> AE manager | D119: =ROUNDDOWN(D118*Macro!$H$26,0) -> 0 | E119: =ROUNDDOWN(E118*Macro!$H$26,0) -> 0 | F119: =ROUNDDOWN(F118*Macro!$H$26,0) -> 0 | G119: =ROUNDDOWN(G118*Macro!$H$26,0) -> 0 | H119: =ROUNDDOWN(H118*Macro!$H$26,0) -> 0 | I119: =ROUNDDOWN(I118*Macro!$H$26,0) -> 0 | J119: =ROUNDDOWN(J118*Macro!$H$26,0) -> 0 | K119: =ROUNDDOWN(K118*Macro!$H$26,0) -> 0 | ... AS119: =ROUNDDOWN(AS118*Macro!$H$26,0) -> 1
C120: =Macro!B60 -> SE | D120: =ROUNDUP(D118*Macro!$H$27,0) -> 1 | E120: =ROUNDUP(E118*Macro!$H$27,0) -> 1 | F120: =ROUNDUP(F118*Macro!$H$27,0) -> 1 | G120: =ROUNDUP(G118*Macro!$H$27,0) -> 1 | H120: =ROUNDUP(H118*Macro!$H$27,0) -> 1 | I120: =ROUNDUP(I118*Macro!$H$27,0) -> 1 | J120: =ROUNDUP(J118*Macro!$H$27,0) -> 1 | K120: =ROUNDUP(K118*Macro!$H$27,0) -> 1 | ... AS120: =ROUNDUP(AS118*Macro!$H$27,0) -> 4
C121: =Macro!B61 -> SE manager | D121: =ROUNDDOWN(D120*Macro!$H$28,0) -> 0 | E121: =ROUNDDOWN(E120*Macro!$H$28,0) -> 0 | F121: =ROUNDDOWN(F120*Macro!$H$28,0) -> 0 | G121: =ROUNDDOWN(G120*Macro!$H$28,0) -> 0 | H121: =ROUNDDOWN(H120*Macro!$H$28,0) -> 0 | I121: =ROUNDDOWN(I120*Macro!$H$28,0) -> 0 | J121: =ROUNDDOWN(J120*Macro!$H$28,0) -> 0 | K121: =ROUNDDOWN(K120*Macro!$H$28,0) -> 0 | ... AS121: =ROUNDDOWN(AS120*Macro!$H$28,0) -> 0
C122: =Macro!B62 -> Sales Ops | D122: 0 | E122: 0 | F122: 0 | G122: 0 | H122: 0 | I122: 0 | J122: 0 | K122: 0 | L122: 0 | M122: 0 | N122: 0 | O122: 0 | P122: 0 | Q122: 0 | R122: 1 | S122: 1 | T122: 1 | U122: 1 | V122: 1 | W122: 1 | X122: 1 | Y122: 1 | Z122: 1 | AA122: 1 | AB122: 1 | AC122: 1 | AD122: 1 | AE122: 1 | AF122: 1 | AG122: 1 | AH122: 1 | AI122: 1 | AJ122: 1 | AK122: 1 | AL122: 1 | AM122: 1 | AN122: 2 | AO122: 2 | AP122: 2 | AQ122: 2 | AR122: 2 | AS122: 2
C123: =Macro!B63 -> [XX] | D123: 0 | E123: 0 | F123: 0 | G123: 0 | H123: 0 | I123: 0 | J123: 0 | K123: 0 | L123: 0 | M123: 0 | N123: 0 | O123: 0 | P123: 0 | Q123: 0 | R123: 0 | S123: 0 | T123: 0 | U123: 0 | V123: 0 | W123: 0 | X123: 0 | Y123: 0 | Z123: 0 | AA123: 0 | AB123: 0 | AC123: 0 | AD123: 0 | AE123: 0 | AF123: 0 | AG123: 0 | AH123: 0 | AI123: 0 | AJ123: 0 | AK123: 0 | AL123: 0 | AM123: 0 | AN123: 0 | AO123: 0 | AP123: 0 | AQ123: 0 | AR123: 0 | AS123: 0
...

Sheet Expenses
A2: =Macro!A2 -> StartUp Co
B3: FY | D3: ='Top line'!D3 -> 2020 | J3: ='Top line'!J3 -> 2021 | V3: ='Top line'!V3 -> 2022 | AH3: ='Top line'!AH3 -> 2023
B4: Quarter | D4: ='Top line'!D4 -> 3 | G4: ='Top line'!G4 -> 4 | J4: ='Top line'!J4 -> 1 | M4: ='Top line'!M4 -> 2 | P4: ='Top line'!P4 -> 3 | S4: ='Top line'!S4 -> 4 | V4: ='Top line'!V4 -> 1 | Y4: ='Top line'!Y4 -> 2 | AB4: ='Top line'!AB4 -> 3 | AE4: ='Top line'!AE4 -> 4 | AH4: ='Top line'!AH4 -> 1 | AK4: ='Top line'!AK4 -> 2 | AN4: ='Top line'!AN4 -> 3 | AQ4: ='Top line'!AQ4 -> 4
B5: Month | D5: ='Top line'!D5 -> 43707 | E5: ='Top line'!E5 -> 43738 | F5: ='Top line'!F5 -> 43769 | G5: ='Top line'!G5 -> 43799 | H5: ='Top line'!H5 -> 43830 | I5: ='Top line'!I5 -> 43861 | J5: ='Top line'!J5 -> 43890 | K5: ='Top line'!K5 -> 43921 | ... AS5: ='Top line'!AS5 -> 44957
D6: Act | E6: Act | F6: Act | G6: Act | H6: Act | I6: Act | J6: Act | K6: Act | L6: Act | M6: Fcst | N6: Fcst | O6: Fcst | P6: Fcst | Q6: Fcst | R6: Fcst | S6: Fcst | T6: Fcst | U6: Fcst | V6: Fcst | W6: Fcst | X6: Fcst | Y6: Fcst | Z6: Fcst | AA6: Fcst | AB6: Fcst | AC6: Fcst | AD6: Fcst | AE6: Fcst | AF6: Fcst | AG6: Fcst | AH6: Fcst | AI6: Fcst | AJ6: Fcst | AK6: Fcst | AL6: Fcst | AM6: Fcst | AN6: Fcst | AO6: Fcst | AP6: Fcst | AQ6: Fcst | AR6: Fcst | AS6: Fcst
B8: Summary
B9: Compensation & Related | J9: =J37 -> 394720 | K9: =K37 -> 394720 | L9: =L37 -> 484720 | M9: =M37 -> #VALUE! | N9: =N37 -> #VALUE! | O9: =O37 -> #VALUE! | P9: =P37 -> #VALUE! | Q9: =Q37 -> #VALUE! | ... AS9: =AS37 -> #VALUE!
B10: Outside Services | J10: =J51 -> 27000 | K10: =K51 -> 27000 | L10: =L51 -> 27000 | M10: =M51 -> 42000 | N10: =N51 -> 42000 | O10: =O51 -> 42000 | P10: =P51 -> 42000 | Q10: =Q51 -> 42000 | ... AS10: =AS51 -> 42000
B11: Employee & Related | J11: =J55 -> 0 | K11: =K55 -> 0 | L11: =L55 -> 0 | M11: =M55 -> 0 | N11: =N55 -> 0 | O11: =O55 -> 0 | P11: =P55 -> 0 | Q11: =Q55 -> 0 | ... AS11: =AS55 -> 0
B12: Travel & Related | J12: =J58 -> 12500 | K12: =K58 -> 12500 | L12: =L58 -> 12500 | M12: =M58 -> 15000 | N12: =N58 -> 15000 | O12: =O58 -> 15000 | P12: =P58 -> 20000 | Q12: =Q58 -> 20000 | ... AS12: =AS58 -> 42500
B13: Marketing Development | J13: =J71 -> 50000 | K13: =K71 -> 50000 | L13: =L71 -> 50000 | M13: =M71 -> 50000 | N13: =N71 -> 50000 | O13: =O71 -> 50000 | P13: =P71 -> 50000 | Q13: =Q71 -> 50000 | ... AS13: =AS71 -> 70000
B14: Facilities, Equipment & Supplies | J14: =J96 -> 45360 | K14: =K96 -> 45360 | L14: =L96 -> 48870 | M14: =M96 -> 48255 | N14: =N96 -> 48640 | O14: =O96 -> 49610 | P14: =P96 -> 50380 | Q14: =Q96 -> 49980 | ... AS14: =AS96 -> 56910
B15: Corporate | J15: =J105 -> 600 | K15: =K105 -> 600 | L15: =L105 -> 750 | M15: =M105 -> 775 | N15: =N105 -> 800 | O15: =O105 -> 850 | P15: =P105 -> 900 | Q15: =Q105 -> 900 | ... AS15: =AS105 -> 1350
B16: Total | J16: =SUM(J9:J15) -> 530180 | K16: =SUM(K9:K15) -> 530180 | L16: =SUM(L9:L15) -> 623840 | M16: =SUM(M9:M15) -> #VALUE! | N16: =SUM(N9:N15) -> #VALUE! | O16: =SUM(O9:O15) -> #VALUE! | P16: =SUM(P9:P15) -> #VALUE! | Q16: =SUM(Q9:Q15) -> #VALUE! | ... AS16: =SUM(AS9:AS15) -> #VALUE!
B18: Cost of Services
B19: COGS - Others | J19: =IFERROR(Macro!$D$46*'Top line'!J30,"NA") -> 0 | K19: =IFERROR(Macro!$D$46*'Top line'!K30,"NA") -> 0 | L19: =IFERROR(Macro!$D$46*'Top line'!L30,"NA") -> 0 | M19: =IFERROR(Macro!$D$46*'Top line'!M30,"NA") -> NA | N19: =IFERROR(Macro!$D$46*'Top line'!N30,"NA") -> NA | O19: =IFERROR(Macro!$D$46*'Top line'!O30,"NA") -> NA | P19: =IFERROR(Macro!$D$46*'Top line'!P30,"NA") -> NA | Q19: =IFERROR(Macro!$D$46*'Top line'!Q30,"NA") -> NA | ... AS19: =IFERROR(Macro!$D$46*'Top line'!AS30,"NA") -> NA
B20: COGS - Hosting services | J20: =IFERROR(Macro!$D$47,"NA") -> 17500 | K20: =IFERROR(Macro!$D$47,"NA") -> 17500 | L20: =IFERROR(Macro!$D$47,"NA") -> 17500 | M20: =IFERROR(Macro!$D$47,"NA") -> 17500 | N20: =IFERROR(Macro!$D$47,"NA") -> 17500 | O20: =IFERROR(Macro!$D$47,"NA") -> 17500 | P20: =IFERROR(Macro!$D$47,"NA") -> 17500 | Q20: =IFERROR(Macro!$D$47,"NA") -> 17500 | ... AS20: =IFERROR(Macro!$D$47,"NA") -> 17500
B21: COGS - Salesforce | J21: =IFERROR('Top line'!J36*Macro!$D$48*Macro!$D$49,"NA") -> 0 | K21: =IFERROR('Top line'!K36*Macro!$D$48*Macro!$D$49,"NA") -> 0 | L21: =IFERROR('Top line'!L36*Macro!$D$48*Macro!$D$49,"NA") -> 0 | M21: =IFERROR('Top line'!M36*Macro!$D$48*Macro!$D$49,"NA") -> 0 | N21: =IFERROR('Top line'!N36*Macro!$D$48*Macro!$D$49,"NA") -> NA | O21: =IFERROR('Top line'!O36*Macro!$D$48*Macro!$D$49,"NA") -> NA | P21: =IFERROR('Top line'!P36*Macro!$D$48*Macro!$D$49,"NA") -> NA | Q21: =IFERROR('Top line'!Q36*Macro!$D$48*Macro!$D$49,"NA") -> NA | ... AS21: =IFERROR('Top line'!AS36*Macro!$D$48*Macro!$D$49,"NA") -> NA
B22: Total | J22: =SUM(J19:J21) -> 17500 | K22: =SUM(K19:K21) -> 17500 | L22: =SUM(L19:L21) -> 17500 | M22: =SUM(M19:M21) -> 17500 | N22: =SUM(N19:N21) -> 17500 | O22: =SUM(O19:O21) -> 17500 | P22: =SUM(P19:P21) -> 17500 | Q22: =SUM(Q19:Q21) -> 17500 | ... AS22: =SUM(AS19:AS21) -> 17500
B24: Debt repayment
B25: Debt paydown
B26: Interest
B28: Capex
B29: =Macro!B212 -> Laptop | J29: =Macro!$D$212*Team!J9 -> 0 | K29: =Macro!$D$212*Team!K9 -> 0 | L29: =Macro!$D$212*Team!L9 -> 9000 | M29: =Macro!$D$212*Team!M9 -> 1500 | N29: =Macro!$D$212*Team!N9 -> 1500 | O29: =Macro!$D$212*Team!O9 -> 3000 | P29: =Macro!$D$212*Team!P9 -> 3000 | Q29: =Macro!$D$212*Team!Q9 -> 0 | ... AS29: =Macro!$D$212*Team!AS9 -> 0
B30: Others
B32: Operating Expenses
B33: Compensation
C34: Salaries | J34: =Team!J11 -> 303333.33 | K34: =Team!K11 -> 303333.33 | L34: =Team!L11 -> 378333.33 | M34: =Team!M11 -> 395000 | N34: =Team!N11 -> 407500 | O34: =Team!O11 -> 432500 | P34: =Team!P11 -> 445833.33 | Q34: =Team!Q11 -> 445833.33 | ... AS34: =Team!AS11 -> 644166.67
C35: Commission - Sales | J35: =Team!J342 -> 25600 | K35: =Team!K342 -> 25600 | L35: =Team!L342 -> 25600 | M35: =Team!M342 -> #VALUE! | N35: =Team!N342 -> #VALUE! | O35: =Team!O342 -> #VALUE! | P35: =Team!P342 -> #VALUE! | Q35: =Team!Q342 -> #VALUE! | ... AS35: =Team!AS342 -> #VALUE!
C36: Benefits & taxes | J36: =Macro!$D$50*(J34+(1-Macro!$D$51)*Expenses!J35) -> 65786.667 | K36: =Macro!$D$50*(K34+(1-Macro!$D$51)*Expenses!K35) -> 65786.667 | L36: =Macro!$D$50*(L34+(1-Macro!$D$51)*Expenses!L35) -> 80786.667 | M36: =Macro!$D$50*(M34+(1-Macro!$D$51)*Expenses!M35) -> #VALUE! | N36: =Macro!$D$50*(N34+(1-Macro!$D$51)*Expenses!N35) -> #VALUE! | O36: =Macro!$D$50*(O34+(1-Macro!$D$51)*Expenses!O35) -> #VALUE! | P36: =Macro!$D$50*(P34+(1-Macro!$D$51)*Expenses!P35) -> #VALUE! | Q36: =Macro!$D$50*(Q34+(1-Macro!$D$51)*Expenses!Q35) -> #VALUE! | ... AS36: =Macro!$D$50*(AS34+(1-Macro!$D$51)*Expenses!AS35) -> #VALUE!
C37: Total | J37: =SUM(J34:J36) -> 394720 | K37: =SUM(K34:K36) -> 394720 | L37: =SUM(L34:L36) -> 484720 | M37: =SUM(M34:M36) -> #VALUE! | N37: =SUM(N34:N36) -> #VALUE! | O37: =SUM(O34:O36) -> #VALUE! | P37: =SUM(P34:P36) -> #VALUE! | Q37: =SUM(Q34:Q36) -> #VALUE! | ... AS37: =SUM(AS34:AS36) -> #VALUE!
B39: Outside Services
C40: Professional services
C41: =Macro!B151 -> Accounting & Payroll | J41: =Macro!$D151 -> 2000 | K41: =Macro!$D151 -> 2000 | L41: =Macro!$D151 -> 2000 | M41: =Macro!$D151 -> 2000 | N41: =Macro!$D151 -> 2000 | O41: =Macro!$D151 -> 2000 | P41: =Macro!$D151 -> 2000 | Q41: =Macro!$D151 -> 2000 | ... AS41: =Macro!$D151 -> 2000
C42: =Macro!B152 -> Audit & Tax | J42: =Macro!$D152 -> 5000 | K42: =Macro!$D152 -> 5000 | L42: =Macro!$D152 -> 5000 | M42: =Macro!$D152 -> 5000 | N42: =Macro!$D152 -> 5000 | O42: =Macro!$D152 -> 5000 | P42: =Macro!$D152 -> 5000 | Q42: =Macro!$D152 -> 5000 | ... AS42: =Macro!$D152 -> 5000
C43: =Macro!B153 -> Outsource Engineers | J43: =Macro!$D153*J53/12 -> 20000 | K43: =Macro!$D153*K53/12 -> 20000 | L43: =Macro!$D153*L53/12 -> 20000 | M43: =Macro!$D153*M53/12 -> 35000 | N43: =Macro!$D153*N53/12 -> 35000 | O43: =Macro!$D153*O53/12 -> 35000 | P43: =Macro!$D153*P53/12 -> 35000 | Q43: =Macro!$D153*Q53/12 -> 35000 | ... AS43: =Macro!$D153*AS53/12 -> 35000
C44: =Macro!B154 -> [X] | J44: =Macro!$D154 | K44: =Macro!$D154 | L44: =Macro!$D154 | M44: =Macro!$D154 | N44: =Macro!$D154 | O44: =Macro!$D154 | P44: =Macro!$D154 | Q44: =Macro!$D154 | ... AS44: =Macro!$D154
C45: =Macro!B155 -> [X] | J45: =Macro!$D155 | K45: =Macro!$D155 | L45: =Macro!$D155 | M45: =Macro!$D155 | N45: =Macro!$D155 | O45: =Macro!$D155 | P45: =Macro!$D155 | Q45: =Macro!$D155 | ... AS45: =Macro!$D155
C46: =Macro!B156 -> [X] | J46: =Macro!$D156 | K46: =Macro!$D156 | L46: =Macro!$D156 | M46: =Macro!$D156 | N46: =Macro!$D156 | O46: =Macro!$D156 | P46: =Macro!$D156 | Q46: =Macro!$D156 | ... AS46: =Macro!$D156
C47: =Macro!B157 -> [X] | J47: =Macro!$D157 | K47: =Macro!$D157 | L47: =Macro!$D157 | M47: =Macro!$D157 | N47: =Macro!$D157 | O47: =Macro!$D157 | P47: =Macro!$D157 | Q47: =Macro!$D157 | ... AS47: =Macro!$D157
C48: =Macro!B158 -> [X] | J48: =Macro!$D158 | K48: =Macro!$D158 | L48: =Macro!$D158 | M48: =Macro!$D158 | N48: =Macro!$D158 | O48: =Macro!$D158 | P48: =Macro!$D158 | Q48: =Macro!$D158 | ... AS48: =Macro!$D158
C49: =Macro!B159 -> [X] | J49: =Macro!$D159 | K49: =Macro!$D159 | L49: =Macro!$D159 | M49: =Macro!$D159 | N49: =Macro!$D159 | O49: =Macro!$D159 | P49: =Macro!$D159 | Q49: =Macro!$D159 | ... AS49: =Macro!$D159
C50: =Macro!B160 -> [X] | J50: =Macro!$D160 | K50: =Macro!$D160 | L50: =Macro!$D160 | M50: =Macro!$D160 | N50: =Macro!$D160 | O50: =Macro!$D160 | P50: =Macro!$D160 | Q50: =Macro!$D160 | ... AS50: =Macro!$D160
C51: Total | D51: 114500.13 | E51: 77423.84 | F51: 76009.79 | G51: 66470.41 | H51: 87812.66 | I51: 83634.88 | J51: =SUM(J40:J50) -> 27000 | K51: =SUM(K40:K50) -> 27000 | L51: =SUM(L40:L50) -> 27000 | M51: =SUM(M40:M50) -> 42000 | N51: =SUM(N40:N50) -> 42000 | O51: =SUM(O40:O50) -> 42000 | P51: =SUM(P40:P50) -> 42000 | Q51: =SUM(Q40:Q50) -> 42000 | ... AS51: =SUM(AS40:AS50) -> 42000
C53: Reference: Outsource Team Count | J53: 4 | K53: 4 | L53: 4 | M53: 7 | N53: 7 | O53: 7 | P53: 7 | Q53: 7 | R53: 7 | S53: 7 | T53: 7 | U53: 7 | V53: 7 | W53: 7 | X53: 7 | Y53: 7 | Z53: 7 | AA53: 7 | AB53: 7 | AC53: 7 | AD53: 7 | AE53: 7 | AF53: 7 | AG53: 7 | AH53: 7 | AI53: 7 | AJ53: 7 | AK53: 7 | AL53: 7 | AM53: 7 | AN53: 7 | AO53: 7 | AP53: 7 | AQ53: 7 | AR53: 7 | AS53: 7
B55: Employee & Related | D55: 690 | E55: 9346.5 | F55: -7 | G55: 2020 | H55: 1740 | I55: 108.99 | J55: =Macro!$D162*Team!J10 -> 0 | K55: =Macro!$D162*Team!K10 -> 0 | L55: =Macro!$D162*Team!L10 -> 0 | M55: =Macro!$D162*Team!M10 -> 0 | N55: =Macro!$D162*Team!N10 -> 0 | O55: =Macro!$D162*Team!O10 -> 0 | P55: =Macro!$D162*Team!P10 -> 0 | Q55: =Macro!$D162*Team!Q10 -> 0 | ... AS55: =Macro!$D162*Team!AS10 -> 0
B57: Travel & Related
C58: =Macro!B165 -> Travelers | D58: 26970.07 | E58: 27956.68 | F58: 6010.3 | G58: 16414.64 | H58: 20635.19 | I58: 12600.36 | J58: =Macro!$D165*Team!J12 -> 12500 | K58: =Macro!$D165*Team!K12 -> 12500 | L58: =Macro!$D165*Team!L12 -> 12500 | M58: =Macro!$D165*Team!M12 -> 15000 | N58: =Macro!$D165*Team!N12 -> 15000 | O58: =Macro!$D165*Team!O12 -> 15000 | P58: =Macro!$D165*Team!P12 -> 20000 | Q58: =Macro!$D165*Team!Q12 -> 20000 | ... AS58: =Macro!$D165*Team!AS12 -> 42500
C59: =Macro!B166 -> Non-Travelers | J59: =Macro!$D$166*Team!J13 -> 1900 | K59: =Macro!$D$166*Team!K13 -> 1900 | L59: =Macro!$D$166*Team!L13 -> 2500 | M59: =Macro!$D$166*Team!M13 -> 2500 | N59: =Macro!$D$166*Team!N13 -> 2600 | O59: =Macro!$D$166*Team!O13 -> 2800 | P59: =Macro!$D$166*Team!P13 -> 2800 | Q59: =Macro!$D$166*Team!Q13 -> 2800 | ... AS59: =Macro!$D$166*Team!AS13 -> 3700
B61: Marketing Development
C62: =Macro!B169 -> FY21 General Allocation | D62: 28117 | E62: 25417 | F62: 33810.55 | G62: 20894.93 | H62: 26611.67 | I62: 25711.67 | J62: =Macro!$D$169 -> 50000 | K62: =Macro!$D$169 -> 50000 | L62: =Macro!$D$169 -> 50000 | M62: =Macro!$D$169 -> 50000 | N62: =Macro!$D$169 -> 50000 | O62: =Macro!$D$169 -> 50000 | P62: =Macro!$D$169 -> 50000 | Q62: =Macro!$D$169 -> 50000 | ... U62: =Macro!$D$169 -> 50000
C63: =Macro!B170 -> FY22 General Allocation | D63: 59239.02 | E63: 49144.73 | G63: 18000 | H63: 15743.05 | I63: 43.72 | V63: =Macro!$D$170 -> 60000 | W63: =Macro!$D$170 -> 60000 | X63: =Macro!$D$170 -> 60000 | Y63: =Macro!$D$170 -> 60000 | Z63: =Macro!$D$170 -> 60000 | AA63: =Macro!$D$170 -> 60000 | AB63: =Macro!$D$170 -> 60000 | AC63: =Macro!$D$170 -> 60000 | ... AG63: =Macro!$D$170 -> 60000
C64: =Macro!B171 -> FY23 General Allocation | D64: 0 | E64: 0 | F64: 0 | G64: 0 | H64: 0 | I64: 0 | AH64: =Macro!$D$171 -> 70000 | AI64: =Macro!$D$171 -> 70000 | AJ64: =Macro!$D$171 -> 70000 | AK64: =Macro!$D$171 -> 70000 | AL64: =Macro!$D$171 -> 70000 | AM64: =Macro!$D$171 -> 70000 | AN64: =Macro!$D$171 -> 70000 | AO64: =Macro!$D$171 -> 70000 | ... AS64: =Macro!$D$171 -> 70000
C65: =Macro!B172 -> [X] | D65: 3166.6667 | E65: 3166.6667 | F65: 3166.6667 | G65: 3166.6667 | H65: 3166.6667 | I65: 3166.6667 | J65: =Macro!$D172 | K65: =Macro!$D172 | L65: =Macro!$D172 | M65: =Macro!$D172 | N65: =Macro!$D172 | O65: =Macro!$D172 | P65: =Macro!$D172 | Q65: =Macro!$D172 | ... AS65: =Macro!$D172
C66: =Macro!B173 -> [X] | D66: 3047.11 | E66: 2617.75 | F66: 3378.31 | G66: 2636.5 | H66: 2632 | I66: 3234.18 | J66: =Macro!$D173 | K66: =Macro!$D173 | L66: =Macro!$D173 | M66: =Macro!$D173 | N66: =Macro!$D173 | O66: =Macro!$D173 | P66: =Macro!$D173 | Q66: =Macro!$D173 | ... AS66: =Macro!$D173
C67: =Macro!B174 -> [X] | D67: 8316.55 | E67: 5224 | F67: 7728.8 | G67: 3224 | H67: 3268.98 | I67: 2584.2 | J67: =Macro!$D174 | K67: =Macro!$D174 | L67: =Macro!$D174 | M67: =Macro!$D174 | N67: =Macro!$D174 | O67: =Macro!$D174 | P67: =Macro!$D174 | Q67: =Macro!$D174 | ... AS67: =Macro!$D174
C68: =Macro!B175 -> [X] | D68: 1666.67 | E68: 1666.67 | F68: 1666.67 | G68: 1666.67 | H68: 2066.67 | I68: 1665.67 | J68: =Macro!$D175 | K68: =Macro!$D175 | L68: =Macro!$D175 | M68: =Macro!$D175 | N68: =Macro!$D175 | O68: =Macro!$D175 | P68: =Macro!$D175 | Q68: =Macro!$D175 | ... AS68: =Macro!$D175
C69: =Macro!B176 -> [X] | G69: 350 | H69: 1500 | I69: 1000 | J69: =Macro!$D176 | K69: =Macro!$D176 | L69: =Macro!$D176 | M69: =Macro!$D176 | N69: =Macro!$D176 | O69: =Macro!$D176 | P69: =Macro!$D176 | Q69: =Macro!$D176 | ... AS69: =Macro!$D176
C70: =Macro!B177 -> [X] | D70: 5 | J70: =Macro!$D177 | K70: =Macro!$D177 | L70: =Macro!$D177 | M70: =Macro!$D177 | N70: =Macro!$D177 | O70: =Macro!$D177 | P70: =Macro!$D177 | Q70: =Macro!$D177 | ... AS70: =Macro!$D177
C71: Total | D71: =SUM(D62:D70) -> 103558.02 | E71: =SUM(E62:E70) -> 87236.817 | F71: =SUM(F62:F70) -> 49750.997 | G71: =SUM(G62:G70) -> 49938.767 | H71: =SUM(H62:H70) -> 54989.037 | I71: =SUM(I62:I70) -> 37406.107 | J71: =SUM(J62:J70) -> 50000 | K71: =SUM(K62:K70) -> 50000 | ... AS71: =SUM(AS62:AS70) -> 70000
B73: Facilities, Equipment & Supplies
C74: Cell phone | J74: =Macro!$D180*Team!J10 -> 2400 | K74: =Macro!$D180*Team!K10 -> 2400 | L74: =Macro!$D180*Team!L10 -> 3000 | M74: =Macro!$D180*Team!M10 -> 3100 | N74: =Macro!$D180*Team!N10 -> 3200 | O74: =Macro!$D180*Team!O10 -> 3400 | P74: =Macro!$D180*Team!P10 -> 3600 | Q74: =Macro!$D180*Team!Q10 -> 3600 | ... AS74: =Macro!$D180*Team!AS10 -> 5400
C75: Software subscription
C76: =Macro!B182 -> Sales | J76: =Macro!$D182 -> 10 | K76: =Macro!$D182 -> 10 | L76: =Macro!$D182 -> 10 | M76: =Macro!$D182 -> 10 | N76: =Macro!$D182 -> 10 | O76: =Macro!$D182 -> 10 | P76: =Macro!$D182 -> 10 | Q76: =Macro!$D182 -> 10 | ... AS76: =Macro!$D182 -> 10
C77: =Macro!B183 -> Marketing | J77: =Macro!$D183 -> 10 | K77: =Macro!$D183 -> 10 | L77: =Macro!$D183 -> 10 | M77: =Macro!$D183 -> 10 | N77: =Macro!$D183 -> 10 | O77: =Macro!$D183 -> 10 | P77: =Macro!$D183 -> 10 | Q77: =Macro!$D183 -> 10 | ... AS77: =Macro!$D183 -> 10
C78: =Macro!B184 -> Engineering | J78: =Macro!$D184 -> 10 | K78: =Macro!$D184 -> 10 | L78: =Macro!$D184 -> 10 | M78: =Macro!$D184 -> 10 | N78: =Macro!$D184 -> 10 | O78: =Macro!$D184 -> 10 | P78: =Macro!$D184 -> 10 | Q78: =Macro!$D184 -> 10 | ... AS78: =Macro!$D184 -> 10
C79: =Macro!B185 -> Product | J79: =Macro!$D185 -> 10 | K79: =Macro!$D185 -> 10 | L79: =Macro!$D185 -> 10 | M79: =Macro!$D185 -> 10 | N79: =Macro!$D185 -> 10 | O79: =Macro!$D185 -> 10 | P79: =Macro!$D185 -> 10 | Q79: =Macro!$D185 -> 10 | ... AS79: =Macro!$D185 -> 10
C80: =Macro!B186 -> Customer Success | J80: =Macro!$D186 -> 10 | K80: =Macro!$D186 -> 10 | L80: =Macro!$D186 -> 10 | M80: =Macro!$D186 -> 10 | N80: =Macro!$D186 -> 10 | O80: =Macro!$D186 -> 10 | P80: =Macro!$D186 -> 10 | Q80: =Macro!$D186 -> 10 | ... AS80: =Macro!$D186 -> 10
C81: =Macro!B187 -> G&A | J81: =Macro!$D187 -> 10 | K81: =Macro!$D187 -> 10 | L81: =Macro!$D187 -> 10 | M81: =Macro!$D187 -> 10 | N81: =Macro!$D187 -> 10 | O81: =Macro!$D187 -> 10 | P81: =Macro!$D187 -> 10 | Q81: =Macro!$D187 -> 10 | ... AS81: =Macro!$D187 -> 10
C82: Equipment
C83: =Macro!B189 -> Sales | J83: =Macro!$D189 -> 10 | K83: =Macro!$D189 -> 10 | L83: =Macro!$D189 -> 10 | M83: =Macro!$D189 -> 10 | N83: =Macro!$D189 -> 10 | O83: =Macro!$D189 -> 10 | P83: =Macro!$D189 -> 10 | Q83: =Macro!$D189 -> 10 | ... AS83: =Macro!$D189 -> 10
C84: =Macro!B190 -> Marketing | J84: =Macro!$D190 -> 10 | K84: =Macro!$D190 -> 10 | L84: =Macro!$D190 -> 10 | M84: =Macro!$D190 -> 10 | N84: =Macro!$D190 -> 10 | O84: =Macro!$D190 -> 10 | P84: =Macro!$D190 -> 10 | Q84: =Macro!$D190 -> 10 | ... AS84: =Macro!$D190 -> 10
C85: =Macro!B191 -> Engineering | J85: =Macro!$D191 -> 10 | K85: =Macro!$D191 -> 10 | L85: =Macro!$D191 -> 10 | M85: =Macro!$D191 -> 10 | N85: =Macro!$D191 -> 10 | O85: =Macro!$D191 -> 10 | P85: =Macro!$D191 -> 10 | Q85: =Macro!$D191 -> 10 | ... AS85: =Macro!$D191 -> 10
C86: =Macro!B192 -> Product | J86: =Macro!$D192 -> 10 | K86: =Macro!$D192 -> 10 | L86: =Macro!$D192 -> 10 | M86: =Macro!$D192 -> 10 | N86: =Macro!$D192 -> 10 | O86: =Macro!$D192 -> 10 | P86: =Macro!$D192 -> 10 | Q86: =Macro!$D192 -> 10 | ... AS86: =Macro!$D192 -> 10
C87: =Macro!B193 -> Customer Success | J87: =Macro!$D193 -> 10 | K87: =Macro!$D193 -> 10 | L87: =Macro!$D193 -> 10 | M87: =Macro!$D193 -> 10 | N87: =Macro!$D193 -> 10 | O87: =Macro!$D193 -> 10 | P87: =Macro!$D193 -> 10 | Q87: =Macro!$D193 -> 10 | ... AS87: =Macro!$D193 -> 10
C88: =Macro!B194 -> G&A | J88: =Macro!$D194 -> 10 | K88: =Macro!$D194 -> 10 | L88: =Macro!$D194 -> 10 | M88: =Macro!$D194 -> 10 | N88: =Macro!$D194 -> 10 | O88: =Macro!$D194 -> 10 | P88: =Macro!$D194 -> 10 | Q88: =Macro!$D194 -> 10 | ... AS88: =Macro!$D194 -> 10
C89: Equipment
C90: =Macro!B196 -> Rent | J90: =Macro!$D196 -> 36000 | K90: =Macro!$D196 -> 36000 | L90: =Macro!$D196 -> 36000 | M90: =Macro!$D196 -> 36000 | N90: =Macro!$D196 -> 36000 | O90: =Macro!$D196 -> 36000 | P90: =Macro!$D196 -> 36000 | Q90: =Macro!$D196 -> 36000 | ... AS90: =Macro!$D196 -> 36000
C91: =Macro!B197 -> Telephone | J91: =Macro!$D197*Team!J$10 -> 2400 | K91: =Macro!$D197*Team!K$10 -> 2400 | L91: =Macro!$D197*Team!L$10 -> 3000 | M91: =Macro!$D197*Team!M$10 -> 3100 | N91: =Macro!$D197*Team!N$10 -> 3200 | O91: =Macro!$D197*Team!O$10 -> 3400 | P91: =Macro!$D197*Team!P$10 -> 3600 | Q91: =Macro!$D197*Team!Q$10 -> 3600 | ... AS91: =Macro!$D197*Team!AS$10 -> 5400
C92: =Macro!B198 -> Online services | J92: =Macro!$D198*Team!J$10 -> 1200 | K92: =Macro!$D198*Team!K$10 -> 1200 | L92: =Macro!$D198*Team!L$10 -> 1500 | M92: =Macro!$D198*Team!M$10 -> 1550 | N92: =Macro!$D198*Team!N$10 -> 1600 | O92: =Macro!$D198*Team!O$10 -> 1700 | P92: =Macro!$D198*Team!P$10 -> 1800 | Q92: =Macro!$D198*Team!Q$10 -> 1800 | ... AS92: =Macro!$D198*Team!AS$10 -> 2700
C93: =Macro!B199 -> Equip & related - new hire | J93: =Macro!$D199*Team!J9 -> 0 | K93: =Macro!$D199*Team!K9 -> 0 | L93: =Macro!$D199*Team!L9 -> 1200 | M93: =Macro!$D199*Team!M9 -> 200 | N93: =Macro!$D199*Team!N9 -> 200 | O93: =Macro!$D199*Team!O9 -> 400 | P93: =Macro!$D199*Team!P9 -> 400 | Q93: =Macro!$D199*Team!Q9 -> 0 | ... AS93: =Macro!$D199*Team!AS9 -> 0
C94: =Macro!B200 -> Equip & related - employee | J94: =Macro!$D200*Team!J10 -> 2400 | K94: =Macro!$D200*Team!K10 -> 2400 | L94: =Macro!$D200*Team!L10 -> 3000 | M94: =Macro!$D200*Team!M10 -> 3100 | N94: =Macro!$D200*Team!N10 -> 3200 | O94: =Macro!$D200*Team!O10 -> 3400 | P94: =Macro!$D200*Team!P10 -> 3600 | Q94: =Macro!$D200*Team!Q10 -> 3600 | ... AS94: =Macro!$D200*Team!AS10 -> 5400
C95: =Macro!B201 -> Office suppplies, insurance, postage | J95: =Macro!$D201*Team!J10 -> 840 | K95: =Macro!$D201*Team!K10 -> 840 | L95: =Macro!$D201*Team!L10 -> 1050 | M95: =Macro!$D201*Team!M10 -> 1085 | N95: =Macro!$D201*Team!N10 -> 1120 | O95: =Macro!$D201*Team!O10 -> 1190 | P95: =Macro!$D201*Team!P10 -> 1260 | Q95: =Macro!$D201*Team!Q10 -> 1260 | ... AS95: =Macro!$D201*Team!AS10 -> 1890
C96: Total | D96: 47172.39 | E96: 44459.69 | F96: 44364.08 | G96: 45400.36 | H96: 44763.86 | I96: 45925.92 | J96: =SUM(J73:J95) -> 45360 | K96: =SUM(K73:K95) -> 45360 | L96: =SUM(L73:L95) -> 48870 | M96: =SUM(M73:M95) -> 48255 | N96: =SUM(N73:N95) -> 48640 | O96: =SUM(O73:O95) -> 49610 | P96: =SUM(P73:P95) -> 50380 | Q96: =SUM(Q73:Q95) -> 49980 | ... AS96: =SUM(AS73:AS95) -> 56910
B98: Corporate
C99: =Macro!B204 -> Misc. | J99: =Macro!$D204*Team!J10 -> 600 | K99: =Macro!$D204*Team!K10 -> 600 | L99: =Macro!$D204*Team!L10 -> 750 | M99: =Macro!$D204*Team!M10 -> 775 | N99: =Macro!$D204*Team!N10 -> 800 | O99: =Macro!$D204*Team!O10 -> 850 | P99: =Macro!$D204*Team!P10 -> 900 | Q99: =Macro!$D204*Team!Q10 -> 900 | ... AS99: =Macro!$D204*Team!AS10 -> 1350
C100: =Macro!B205 -> [XX] | J100: =Macro!$D205 | K100: =Macro!$D205 | L100: =Macro!$D205 | M100: =Macro!$D205 | N100: =Macro!$D205 | O100: =Macro!$D205 | P100: =Macro!$D205 | Q100: =Macro!$D205 | ... AS100: =Macro!$D205
C101: =Macro!B206 -> [XX] | J101: =Macro!$D206 | K101: =Macro!$D206 | L101: =Macro!$D206 | M101: =Macro!$D206 | N101: =Macro!$D206 | O101: =Macro!$D206 | P101: =Macro!$D206 | Q101: =Macro!$D206 | ... AS101: =Macro!$D206
C102: =Macro!B207 -> [XX] | J102: =Macro!$D207 | K102: =Macro!$D207 | L102: =Macro!$D207 | M102: =Macro!$D207 | N102: =Macro!$D207 | O102: =Macro!$D207 | P102: =Macro!$D207 | Q102: =Macro!$D207 | ... AS102: =Macro!$D207
C103: =Macro!B208 -> [XX] | J103: =Macro!$D208 | K103: =Macro!$D208 | L103: =Macro!$D208 | M103: =Macro!$D208 | N103: =Macro!$D208 | O103: =Macro!$D208 | P103: =Macro!$D208 | Q103: =Macro!$D208 | ... AS103: =Macro!$D208
C104: =Macro!B209 -> [XX] | J104: =Macro!$D209 | K104: =Macro!$D209 | L104: =Macro!$D209 | M104: =Macro!$D209 | N104: =Macro!$D209 | O104: =Macro!$D209 | P104: =Macro!$D209 | Q104: =Macro!$D209 | ... AS104: =Macro!$D209
C105: Total | D105: 2470.84 | E105: 3651.79 | F105: 2733.8206 | G105: 5791.61 | H105: 7131.8546 | I105: 1616.47 | J105: =SUM(J99:J104) -> 600 | K105: =SUM(K99:K104) -> 600 | L105: =SUM(L99:L104) -> 750 | M105: =SUM(M99:M104) -> 775 | N105: =SUM(N99:N104) -> 800 | O105: =SUM(O99:O104) -> 850 | P105: =SUM(P99:P104) -> 900 | Q105: =SUM(Q99:Q104) -> 900 | ... AS105: =SUM(AS99:AS104) -> 1350
B107: Non-Compensation GTM Allocation (Reference only)
B108: Commission
C109: Sales | J109: =J35 -> 25600 | K109: =K35 -> 25600 | L109: =L35 -> 25600 | M109: =M35 -> #VALUE! | N109: =N35 -> #VALUE! | O109: =O35 -> #VALUE! | P109: =P35 -> #VALUE! | Q109: =Q35 -> #VALUE! | ... AS109: =AS35 -> #VALUE!
C110: Marketing | J110: 0 | K110: 0 | L110: 0 | M110: 0 | N110: 0 | O110: 0 | P110: 0 | Q110: 0 | R110: 0 | S110: 0 | T110: 0 | U110: 0 | V110: 0 | W110: 0 | X110: 0 | Y110: 0 | Z110: 0 | AA110: 0 | AB110: 0 | AC110: 0 | AD110: 0 | AE110: 0 | AF110: 0 | AG110: 0 | AH110: 0 | AI110: 0 | AJ110: 0 | AK110: 0 | AL110: 0 | AM110: 0 | AN110: 0 | AO110: 0 | AP110: 0 | AQ110: 0 | AR110: 0 | AS110: 0
C111: Customer Success | J111: 0 | K111: 0 | L111: 0 | M111: 0 | N111: 0 | O111: 0 | P111: 0 | Q111: 0 | R111: 0 | S111: 0 | T111: 0 | U111: 0 | V111: 0 | W111: 0 | X111: 0 | Y111: 0 | Z111: 0 | AA111: 0 | AB111: 0 | AC111: 0 | AD111: 0 | AE111: 0 | AF111: 0 | AG111: 0 | AH111: 0 | AI111: 0 | AJ111: 0 | AK111: 0 | AL111: 0 | AM111: 0 | AN111: 0 | AO111: 0 | AP111: 0 | AQ111: 0 | AR111: 0 | AS111: 0
B113: Outside Services
C114: Sales | J114: =SUMIF(Macro!$F$151:$F$160,Expenses!$C114,Expenses!J$41:J$50) -> 0 | K114: =SUMIF(Macro!$F$151:$F$160,Expenses!$C114,Expenses!K$41:K$50) -> 0 | L114: =SUMIF(Macro!$F$151:$F$160,Expenses!$C114,Expenses!L$41:L$50) -> 0 | M114: =SUMIF(Macro!$F$151:$F$160,Expenses!$C114,Expenses!M$41:M$50) -> 0 | N114: =SUMIF(Macro!$F$151:$F$160,Expenses!$C114,Expenses!N$41:N$50) -> 0 | O114: =SUMIF(Macro!$F$151:$F$160,Expenses!$C114,Expenses!O$41:O$50) -> 0 | P114: =SUMIF(Macro!$F$151:$F$160,Expenses!$C114,Expenses!P$41:P$50) -> 0 | Q114: =SUMIF(Macro!$F$151:$F$160,Expenses!$C114,Expenses!Q$41:Q$50) -> 0 | ... AS114: =SUMIF(Macro!$F$151:$F$160,Expenses!$C114,Expenses!AS$41:AS$50) -> 0
C115: Marketing | J115: =SUMIF(Macro!$F$151:$F$160,Expenses!$C115,Expenses!J$41:J$50) -> 0 | K115: =SUMIF(Macro!$F$151:$F$160,Expenses!$C115,Expenses!K$41:K$50) -> 0 | L115: =SUMIF(Macro!$F$151:$F$160,Expenses!$C115,Expenses!L$41:L$50) -> 0 | M115: =SUMIF(Macro!$F$151:$F$160,Expenses!$C115,Expenses!M$41:M$50) -> 0 | N115: =SUMIF(Macro!$F$151:$F$160,Expenses!$C115,Expenses!N$41:N$50) -> 0 | O115: =SUMIF(Macro!$F$151:$F$160,Expenses!$C115,Expenses!O$41:O$50) -> 0 | P115: =SUMIF(Macro!$F$151:$F$160,Expenses!$C115,Expenses!P$41:P$50) -> 0 | Q115: =SUMIF(Macro!$F$151:$F$160,Expenses!$C115,Expenses!Q$41:Q$50) -> 0 | ... AS115: =SUMIF(Macro!$F$151:$F$160,Expenses!$C115,Expenses!AS$41:AS$50) -> 0
...

Sheet Cash analysis
A2: =Macro!A2 -> StartUp Co
B3: FY | D3: ='Top line'!D3 -> 2020 | J3: ='Top line'!J3 -> 2021 | V3: ='Top line'!V3 -> 2022 | AH3: ='Top line'!AH3 -> 2023
B4: Quarter | D4: ='Top line'!D4 -> 3 | G4: ='Top line'!G4 -> 4 | J4: ='Top line'!J4 -> 1 | M4: ='Top line'!M4 -> 2 | P4: ='Top line'!P4 -> 3 | S4: ='Top line'!S4 -> 4 | V4: ='Top line'!V4 -> 1 | Y4: ='Top line'!Y4 -> 2 | AB4: ='Top line'!AB4 -> 3 | AE4: ='Top line'!AE4 -> 4 | AH4: ='Top line'!AH4 -> 1 | AK4: ='Top line'!AK4 -> 2 | AN4: ='Top line'!AN4 -> 3 | AQ4: ='Top line'!AQ4 -> 4
B5: Month | D5: ='Top line'!D5 -> 43707 | E5: ='Top line'!E5 -> 43738 | F5: ='Top line'!F5 -> 43769 | G5: ='Top line'!G5 -> 43799 | H5: ='Top line'!H5 -> 43830 | I5: ='Top line'!I5 -> 43861 | J5: ='Top line'!J5 -> 43890 | K5: ='Top line'!K5 -> 43921 | ... AS5: ='Top line'!AS5 -> 44957
D6: Act | E6: Act | F6: Act | G6: Act | H6: Act | I6: Act | J6: Act | K6: Act | L6: Act | M6: Fcst | N6: Fcst | O6: Fcst | P6: Fcst | Q6: Fcst | R6: Fcst | S6: Fcst | T6: Fcst | U6: Fcst | V6: Fcst | W6: Fcst | X6: Fcst | Y6: Fcst | Z6: Fcst | AA6: Fcst | AB6: Fcst | AC6: Fcst | AD6: Fcst | AE6: Fcst | AF6: Fcst | AG6: Fcst | AH6: Fcst | AI6: Fcst | AJ6: Fcst | AK6: Fcst | AL6: Fcst | AM6: Fcst | AN6: Fcst | AO6: Fcst | AP6: Fcst | AQ6: Fcst | AR6: Fcst | AS6: Fcst
B8: Cash inflow
C9: Collections | G9: 160000 | H9: 160000 | I9: 160000 | J9: 160000 | K9: 160000 | L9: 300000 | M9: ='Top line'!M36 -> 160000 | N9: ='Top line'!N36 -> #VALUE! | O9: ='Top line'!O36 -> #VALUE! | P9: ='Top line'!P36 -> #VALUE! | Q9: ='Top line'!Q36 -> #VALUE! | R9: ='Top line'!R36 -> #VALUE! | S9: ='Top line'!S36 -> #VALUE! | T9: ='Top line'!T36 -> #VALUE! | ... AS9: ='Top line'!AS36 -> #VALUE!
C10: New financing | G10: 0 | H10: 0 | I10: 0 | J10: 0 | K10: 0 | L10: 0 | M10: =IFERROR(VLOOKUP(M5,Macro!$D$216:$E$218,2,FALSE),0) -> 5000000 | N10: =IFERROR(VLOOKUP(N5,Macro!$D$216:$E$218,2,FALSE),0) -> 0 | O10: =IFERROR(VLOOKUP(O5,Macro!$D$216:$E$218,2,FALSE),0) -> 0 | P10: =IFERROR(VLOOKUP(P5,Macro!$D$216:$E$218,2,FALSE),0) -> 0 | Q10: =IFERROR(VLOOKUP(Q5,Macro!$D$216:$E$218,2,FALSE),0) -> 0 | R10: =IFERROR(VLOOKUP(R5,Macro!$D$216:$E$218,2,FALSE),0) -> 0 | S10: =IFERROR(VLOOKUP(S5,Macro!$D$216:$E$218,2,FALSE),0) -> 0 | T10: =IFERROR(VLOOKUP(T5,Macro!$D$216:$E$218,2,FALSE),0) -> 0 | ... AS10: =IFERROR(VLOOKUP(AS5,Macro!$D$216:$E$218,2,FALSE),0) -> 0
C11: Total | G11: =SUM(G9:G10) -> 160000 | H11: =SUM(H9:H10) -> 160000 | I11: =SUM(I9:I10) -> 160000 | J11: =SUM(J9:J10) -> 160000 | K11: =SUM(K9:K10) -> 160000 | L11: =SUM(L9:L10) -> 300000 | M11: =SUM(M9:M10) -> 5160000 | N11: =SUM(N9:N10) -> #VALUE! | ... AS11: =SUM(AS9:AS10) -> #VALUE!
B13: Cash outflow
C14: Cost of sales | G14: 17500 | H14: 17500 | I14: 17500 | J14: 17500 | K14: 17500 | L14: 17500 | M14: =Expenses!M22 -> 17500 | N14: =Expenses!N22 -> 17500 | O14: =Expenses!O22 -> 17500 | P14: =Expenses!P22 -> 17500 | Q14: =Expenses!Q22 -> 17500 | R14: =Expenses!R22 -> 17500 | S14: =Expenses!S22 -> 17500 | T14: =Expenses!T22 -> 17500 | ... AS14: =Expenses!AS22 -> 17500
C15: Operating expenses | G15: 530060 | H15: 530060 | I15: 530060 | J15: 530060 | K15: 530060 | L15: 623720 | M15: =Expenses!M16 -> #VALUE! | N15: =Expenses!N16 -> #VALUE! | O15: =Expenses!O16 -> #VALUE! | P15: =Expenses!P16 -> #VALUE! | Q15: =Expenses!Q16 -> #VALUE! | R15: =Expenses!R16 -> #VALUE! | S15: =Expenses!S16 -> #VALUE! | T15: =Expenses!T16 -> #VALUE! | ... AS15: =Expenses!AS16 -> #VALUE!
C16: Interest expense | G16: 0 | H16: 0 | I16: 0 | J16: 0 | K16: 0 | L16: 0 | M16: =Expenses!M26 | N16: =Expenses!N26 | O16: =Expenses!O26 | P16: =Expenses!P26 | Q16: =Expenses!Q26 | R16: =Expenses!R26 | S16: =Expenses!S26 | T16: =Expenses!T26 | ... AS16: =Expenses!AS26
C17: Debt paydown | G17: 0 | H17: 0 | I17: 0 | J17: 0 | K17: 0 | L17: 0 | M17: =Expenses!M25 | N17: =Expenses!N25 | O17: =Expenses!O25 | P17: =Expenses!P25 | Q17: =Expenses!Q25 | R17: =Expenses!R25 | S17: =Expenses!S25 | T17: =Expenses!T25 | ... AS17: =Expenses!AS25
C18: Capex | G18: 0 | H18: 0 | I18: 0 | J18: 0 | K18: 0 | L18: 9000 | M18: =SUM(Expenses!M29:M30) -> 1500 | N18: =SUM(Expenses!N29:N30) -> 1500 | O18: =SUM(Expenses!O29:O30) -> 3000 | P18: =SUM(Expenses!P29:P30) -> 3000 | Q18: =SUM(Expenses!Q29:Q30) -> 0 | R18: =SUM(Expenses!R29:R30) -> 3000 | S18: =SUM(Expenses!S29:S30) -> 1500 | T18: =SUM(Expenses!T29:T30) -> 0 | ... AS18: =SUM(Expenses!AS29:AS30) -> 0
C19: Total | G19: =SUM(G14:G18) -> 547560 | H19: =SUM(H14:H18) -> 547560 | I19: =SUM(I14:I18) -> 547560 | J19: =SUM(J14:J18) -> 547560 | K19: =SUM(K14:K18) -> 547560 | L19: =SUM(L14:L18) -> 650220 | M19: =SUM(M14:M18) -> #VALUE! | N19: =SUM(N14:N18) -> #VALUE! | ... AS19: =SUM(AS14:AS18) -> #VALUE!
B21: Beginning cash | G21: 3000000 | H21: =G23 -> 2612440 | I21: =H23 -> 2224880 | J21: =I23 -> 1837320 | K21: =J23 -> 1449760 | L21: =K23 -> 1062200 | M21: =L23 -> 711980 | N21: =M23 -> #VALUE! | O21: =N23 -> #VALUE! | ... AS21: =AR23 -> #VALUE!
B22: Net cash flow | G22: =G11-G19 -> -387560 | H22: =H11-H19 -> -387560 | I22: =I11-I19 -> -387560 | J22: =J11-J19 -> -387560 | K22: =K11-K19 -> -387560 | L22: =L11-L19 -> -350220 | M22: =M11-M19 -> #VALUE! | N22: =N11-N19 -> #VALUE! | ... AS22: =AS11-AS19 -> #VALUE!
B23: Ending cash | G23: =SUM(G21:G22) -> 2612440 | H23: =SUM(H21:H22) -> 2224880 | I23: =SUM(I21:I22) -> 1837320 | J23: =SUM(J21:J22) -> 1449760 | K23: =SUM(K21:K22) -> 1062200 | L23: =SUM(L21:L22) -> 711980 | M23: =SUM(M21:M22) -> #VALUE! | N23: =SUM(N21:N22) -> #VALUE! | ... AS23: =SUM(AS21:AS22) -> #VALUE!
B24: Flag if below threshold | M24: =IF(M23<Macro!$D$6,1,0) -> #VALUE! | N24: =IF(N23<Macro!$D$6,1,0) -> #VALUE! | O24: =IF(O23<Macro!$D$6,1,0) -> #VALUE! | P24: =IF(P23<Macro!$D$6,1,0) -> #VALUE! | Q24: =IF(Q23<Macro!$D$6,1,0) -> #VALUE! | R24: =IF(R23<Macro!$D$6,1,0) -> #VALUE! | S24: =IF(S23<Macro!$D$6,1,0) -> #VALUE! | T24: =IF(T23<Macro!$D$6,1,0) -> #VALUE! | ... AS24: =IF(AS23<Macro!$D$6,1,0) -> #VALUE!
B25: Net cash flow excl. financing | G25: =G22-G10 -> -387560 | H25: =H22-H10 -> -387560 | I25: =I22-I10 -> -387560 | J25: =J22-J10 -> -387560 | K25: =K22-K10 -> -387560 | L25: =L22-L10 -> -350220 | M25: =M22-M10 -> #VALUE! | N25: =N22-N10 -> #VALUE! | ... AS25: =AS22-AS10 -> #VALUE!
I76: 4

Sheet Charts>>
A1: Shasta SaaS Operating Model Charts for comments and questions, contact Kenn So

Sheet 2-year
A2: =Macro!A2 -> StartUp Co
B3: FY | D3: ='Top line'!D3 -> 2020 | J3: ='Top line'!J3 -> 2021 | V3: ='Top line'!V3 -> 2022 | AH3: ='Top line'!AH3 -> 2023
C4: Quarter | D4: ='Top line'!D4 -> 3 | G4: ='Top line'!G4 -> 4 | J4: ='Top line'!J4 -> 1 | M4: ='Top line'!M4 -> 2 | P4: ='Top line'!P4 -> 3 | S4: ='Top line'!S4 -> 4 | V4: ='Top line'!V4 -> 1 | Y4: ='Top line'!Y4 -> 2 | AB4: ='Top line'!AB4 -> 3 | AE4: ='Top line'!AE4 -> 4 | AH4: ='Top line'!AH4 -> 1 | AK4: ='Top line'!AK4 -> 2 | AN4: ='Top line'!AN4 -> 3 | AQ4: ='Top line'!AQ4 -> 4
C5: Month | D5: ='Top line'!D5 -> 43707 | E5: ='Top line'!E5 -> 43738 | F5: ='Top line'!F5 -> 43769 | G5: ='Top line'!G5 -> 43799 | H5: ='Top line'!H5 -> 43830 | I5: ='Top line'!I5 -> 43861 | J5: ='Top line'!J5 -> 43890 | K5: ='Top line'!K5 -> 43921 | ... AS5: ='Top line'!AS5 -> 44957
D6: Act | E6: Act | F6: Act | G6: Act | H6: Act | I6: Act | J6: Act | K6: Act | L6: Act | M6: Fcst | N6: Fcst | O6: Fcst | P6: Fcst | Q6: Fcst | R6: Fcst | S6: Fcst | T6: Fcst | U6: Fcst | V6: Fcst | W6: Fcst | X6: Fcst | Y6: Fcst | Z6: Fcst | AA6: Fcst | AB6: Fcst | AC6: Fcst | AD6: Fcst | AE6: Fcst | AF6: Fcst | AG6: Fcst | AH6: Fcst | AI6: Fcst | AJ6: Fcst | AK6: Fcst | AL6: Fcst | AM6: Fcst | AN6: Fcst | AO6: Fcst | AP6: Fcst | AQ6: Fcst | AR6: Fcst | AS6: Fcst
B8: Key metrics
C9: ARR | G9: ='Top line'!G39 -> 110000 | H9: ='Top line'!H39 -> 160000 | I9: ='Top line'!I39 -> 210000 | J9: ='Top line'!J39 -> 350000 | K9: ='Top line'!K39 -> 490000 | L9: ='Top line'!L39 -> 630000 | M9: ='Top line'!M39 -> #VALUE! | N9: ='Top line'!N39 -> #VALUE! | ... AS9: ='Top line'!AS39 -> #VALUE!
C10: Existing ARR | J10: =I9 -> 210000 | K10: =J9 -> 350000 | L10: =K9 -> 490000 | M10: =L9 -> 630000 | N10: =M9 -> #VALUE! | O10: =N9 -> #VALUE! | P10: =O9 -> #VALUE! | Q10: =P9 -> #VALUE! | ... AS10: =AR9 -> #VALUE!
C11: New ARR | J11: =J9-J10 -> 140000 | K11: =K9-K10 -> 140000 | L11: =L9-L10 -> 140000 | M11: =M9-M10 -> #VALUE! | N11: =N9-N10 -> #VALUE! | O11: =O9-O10 -> #VALUE! | P11: =P9-P10 -> #VALUE! | Q11: =Q9-Q10 -> #VALUE! | ... AS11: =AS9-AS10 -> #VALUE!
C12: Net cash burn (excl. financing, LHS) | J12: =-'Cash analysis'!J25 -> 387560 | K12: =-'Cash analysis'!K25 -> 387560 | L12: =-'Cash analysis'!L25 -> 350220 | M12: =-'Cash analysis'!M25 -> #VALUE! | N12: =-'Cash analysis'!N25 -> #VALUE! | O12: =-'Cash analysis'!O25 -> #VALUE! | P12: =-'Cash analysis'!P25 -> #VALUE! | Q12: =-'Cash analysis'!Q25 -> #VALUE! | ... AS12: =-'Cash analysis'!AS25 -> #VALUE!
C13: Ending Cash (RHS) | G13: =IFERROR('Cash analysis'!G23,"NA") -> 2612440 | H13: =IFERROR('Cash analysis'!H23,"NA") -> 2224880 | I13: =IFERROR('Cash analysis'!I23,"NA") -> 1837320 | J13: =IFERROR('Cash analysis'!J23,"NA") -> 1449760 | K13: =IFERROR('Cash analysis'!K23,"NA") -> 1062200 | L13: =IFERROR('Cash analysis'!L23,"NA") -> 711980 | M13: =IFERROR('Cash analysis'!M23,"NA") -> NA | N13: =IFERROR('Cash analysis'!N23,"NA") -> NA | ... AS13: =IFERROR('Cash analysis'!AS23,"NA") -> NA

Sheet Cash Summary
C3: Base | D3: High | E3: Low
C4: 15K Landing ACV 3.5 deals/month/AE 15% customers upsell 25% upsell value | D4: 20K Landing ACV 4 deals/month/AE 20% customers upsell 30% upsell value | E4: 10K Landing ACV 3 deals/month/AE 10% customers upsell 20% upsell value
B6: Cash end-of-period
B7: 43831 | C7: ='Cash analysis'!X23 -> #VALUE! | D7: ='Cash analysis'!#REF! -> #ERROR! | E7: ='Cash analysis'!#REF! -> #ERROR!
B8: 43922 | C8: ='Cash analysis'!AA23 -> #VALUE! | D8: ='Cash analysis'!#REF! -> #ERROR! | E8: ='Cash analysis'!#REF! -> #ERROR!
B9: 44013 | C9: ='Cash analysis'!AD23 -> #VALUE! | D9: ='Cash analysis'!#REF! -> #ERROR! | E9: ='Cash analysis'!#REF! -> #ERROR!
B11: Collections
B12: Q4 2019 (end Apr-2019) | C12: =SUM('Cash analysis'!M9:O9) -> #VALUE! | D12: =SUM('Cash analysis'!#REF!) -> #ERROR! | E12: =SUM('Cash analysis'!#REF!) -> #ERROR!
B13: Q1 2020 (end Jul-2019) | C13: =SUM('Cash analysis'!P9:R9) -> #VALUE! | D13: =SUM('Cash analysis'!#REF!) -> #ERROR! | E13: =SUM('Cash analysis'!#REF!) -> #ERROR!
B14: Q2 2020 (end Oct-2019) | C14: =SUM('Cash analysis'!S9:U9) -> #VALUE! | D14: =SUM('Cash analysis'!#REF!) -> #ERROR! | E14: =SUM('Cash analysis'!#REF!) -> #ERROR!
B16: ARR end-of-period
B17: 43556 | C17: ='Top line'!O44 -> #VALUE! | D17: ='Top line'!#REF! -> #ERROR! | E17: ='Top line'!#REF! -> #ERROR!
B18: 43647 | C18: ='Top line'!R44 -> #VALUE! | D18: ='Top line'!#REF! -> #ERROR! | E18: ='Top line'!#REF! -> #ERROR!
B19: 43739 | C19: ='Top line'!U44 -> #VALUE! | D19: ='Top line'!#REF! -> #ERROR! | E19: ='Top line'!#REF! -> #ERROR!
